Workbook

Sheet Product List
A2: ABATEMENT/REMEDIATION/ASBESTOS | B2: 01u6S000018BAIdQAO | C2: 01t6S00000BhEQIQA3
A3: ADU | B3: 01u6S00001842qmQAA | C3: 01t6S00000BGzOMQA1
A4: APPLIANCES | B4: 01u6S000016ZYr8QAG | C4: 01t6S00000BGmgVQAT
A5: ARCHITECTURAL AND ENGINEERING | B5: 01u6S000016ZYrpQAG | C5: 01t6S00000BGmgXQAT
A6: BATHROOM | B6: 01u6S000018BAIeQAO | C6: 01t6S00000BhEQJQA3
A7: BUILDING CLEAN-UP | B7: 01u6S000016ZYroQAG | C7: 01t6S00000BGmhEQAT
A8: CABINETS | B8: 01u6S000016ZYrnQAG | C8: 01t6S00000BGmgUQAT
A9: COMPLETION AND INSPECTION | B9: 01u6S000016ZYrlQAG | C9: 01t6S00000BGmggQAD
A10: CONCRETE | B10: 01u6S000016ZYrkQAG | C10: 01t6S00000BGmgxQAD
A11: CONCRETE SUBFLOOR | B11: 01u6S00001844JrQAI | C11: 01t6S00000BH1bXQAT
A12: CONCRETE WALL | B12: 01u6S00001844JsQAI | C12: 01t6S00000BH1bTQAT
A13: CONTINGENCY | B13: 01u6S000016ZYrjQAG | C13: 01t6S00000BGmgfQAD
... A97: WINDOWS AND DOORS | B97: 01u6S000016ZYs5QAG | C97: 01t6S00000BGmh6QAD

Sheet Arixa SOV
A1: Price Book Entry ID | B1: Product ID | C1: Product DO NOT MAP | D1: Opportunity ID
A2: =IFERROR(VLOOKUP(C2,'Product List'!$A$2:$C198,2,FALSE),"") | B2: =IFERROR(VLOOKUP(C2,'Product List'!$A$2:$C198,3,FALSE),"")
A3: =IFERROR(VLOOKUP(C3,'Product List'!$A$2:$C198,2,FALSE),"") | B3: =IFERROR(VLOOKUP(C3,'Product List'!$A$2:$C198,3,FALSE),"")
A4: =IFERROR(VLOOKUP(C4,'Product List'!$A$2:$C198,2,FALSE),"") | B4: =IFERROR(VLOOKUP(C4,'Product List'!$A$2:$C198,3,FALSE),"")
A5: =IFERROR(VLOOKUP(C5,'Product List'!$A$2:$C198,2,FALSE),"") | B5: =IFERROR(VLOOKUP(C5,'Product List'!$A$2:$C198,3,FALSE),"")
A6: =IFERROR(VLOOKUP(C6,'Product List'!$A$2:$C198,2,FALSE),"") | B6: =IFERROR(VLOOKUP(C6,'Product List'!$A$2:$C198,3,FALSE),"") | F6: Property Address: | G6: 1075 Century Drive, Ogden, UT 84404 | S6: Construction Loan Amount: | T6: =G190 -> 16921419 | W6: Expected Completion Date:
A7: =IFERROR(VLOOKUP(C7,'Product List'!$A$2:$C198,2,FALSE),"") | B7: =IFERROR(VLOOKUP(C7,'Product List'!$A$2:$C198,3,FALSE),"") | F7: Borrower Name: | G7: Hunter's Landing North, LLC - Aubrey Palmer (PALMER AUBREY) | O7: Phone: | P7: (801) 400-8452 | S7: Remaining Balance Post Draw: | T7: =N190 -> 11494705 | W7: Draw Reimbursement % | Y7: 1
A8: =IFERROR(VLOOKUP(C8,'Product List'!$A$2:$C198,2,FALSE),"") | B8: =IFERROR(VLOOKUP(C8,'Product List'!$A$2:$C198,3,FALSE),"") | F8: Draw Point Of Contact | G8: - | O8: Phone: | S8: Lock Box | W8: Draw Fee Adjusted: | Y8: =SUM(T10/Y7) -> 500
A9: =IFERROR(VLOOKUP(C9,'Product List'!$A$2:$C198,2,FALSE),"") | B9: =IFERROR(VLOOKUP(C9,'Product List'!$A$2:$C198,3,FALSE),"") | F9: General Contractor: | O9: License: | S9: Project Square Footage | T9: 82227
A10: =IFERROR(VLOOKUP(C10,'Product List'!$A$2:$C198,2,FALSE),"") | B10: =IFERROR(VLOOKUP(C10,'Product List'!$A$2:$C198,3,FALSE),"") | F10: Inspectors Name: | O10: Phone: | S10: Draw Processing Fee: | T10: 500
A11: =IFERROR(VLOOKUP(C11,'Product List'!$A$2:$C198,2,FALSE),"") | B11: =IFERROR(VLOOKUP(C11,'Product List'!$A$2:$C198,3,FALSE),"")
A12: =IFERROR(VLOOKUP(C12,'Product List'!$A$2:$C198,2,FALSE),"") | B12: =IFERROR(VLOOKUP(C12,'Product List'!$A$2:$C198,3,FALSE),"")
A13: =IFERROR(VLOOKUP(C13,'Product List'!$A$2:$C198,2,FALSE),"") | B13: =IFERROR(VLOOKUP(C13,'Product List'!$A$2:$C198,3,FALSE),"") | E13: Item | F13: Description | G13: Budget | H13: Pre-Funding | I13: Approved | J13: Reallocation | K13: Revised Ready for Draw 1 | L13: % | M13: $ PSF | N13: Balance | O13: Draw #1 | P13: Draw #2 | Q13: Draw #3 | R13: Draw #4 | S13: Draw #5 | T13: Draw #6 | U13: Draw #7 | V13: Draw #8 | W13: Draw #9 | X13: Draw #10 | Y13: Draw #11 | Z13: Draw #12 | AA13: Draw #13 | AB13: Draw #14 | AC13: Draw #15 | AD13: Draw #16 | AE13: Draw #17 | AF13: Draw #18 | AG13: Draw #19 | AH13: Draw #20 | AI13: Draw #21 | AJ13: Draw #22 | AK13: Draw #23 | AL13: Retainage | AM13: Costs-to-Date | AN13: %
A14: =IFERROR(VLOOKUP(C14,'Product List'!$A$2:$C198,2,FALSE),"") | B14: =IFERROR(VLOOKUP(C14,'Product List'!$A$2:$C198,3,FALSE),"") | E14: # | G14: Amount | H14: Costs-to-Date & Contributed costs | I14: Current | J14: (+/-) | K14: Budget | L14: Of | M14: Of | N14: Remaining | O14: Amount(s) | P14: Amount(s) | Q14: Amount(s) | R14: Amount(s) | S14: Amount(s) | T14: Amount(s) | U14: Amount(s) | V14: Amount(s) | W14: Amount(s) | X14: Amount(s) | Y14: Amount(s) | Z14: Amount(s) | AA14: Amount(s) | AB14: Amount(s) | AC14: Amount(s) | AD14: Amount(s) | AE14: Amount(s) | AF14: Amount(s) | AG14: Amount(s) | AH14: Amount(s) | AI14: Amount(s) | AJ14: Amount(s) | AK14: Amount(s) | AN14: Drawn
A15: =IFERROR(VLOOKUP(C15,'Product List'!$A$2:$C198,2,FALSE),"") | B15: =IFERROR(VLOOKUP(C15,'Product List'!$A$2:$C198,3,FALSE),"") | H15: (Non Reimbursable) | I15: Budget | L15: Revised | M15: Revised
A16: =IFERROR(VLOOKUP(C16,'Product List'!$A$2:$C198,2,FALSE),"") | B16: =IFERROR(VLOOKUP(C16,'Product List'!$A$2:$C198,3,FALSE),"") | E16: 1 | F16: Survey | G16: 7000 | H16: 0 | I16: =+G16-H16 -> 7000 | J16: 0 | K16: =+I16+J16 -> 7000 | L16: =+K16/$K$190 -> 0.00050359712 | M16: =+K16/$T$9 -> 0.085130188 | N16: =+K16-SUM(O16:AL16) -> 7000 | O16: 0 | P16: 0 | Q16: 0 | R16: 0 | S16: 0 | T16: 0 | U16: 0 | V16: 0 | W16: 0 | X16: 0 | Y16: 0 | Z16: 0 | AA16: 0 | AB16: 0 | AC16: 0 | AD16: 0 | AE16: 0 | AF16: 0 | AG16: 0 | AH16: 0 | AI16: 0 | AJ16: 0 | AK16: 0 | AM16: =SUM(O16:AL16) -> 0 | AN16: =IF(K16=0,"",(K16-N16-AL16)/K16) -> 0
A17: =IFERROR(VLOOKUP(C17,'Product List'!$A$2:$C198,2,FALSE),"") | B17: =IFERROR(VLOOKUP(C17,'Product List'!$A$2:$C198,3,FALSE),"") | E17: =+E16+1 -> 2 | F17: Excavation of building and site, backfill, sewer & water connections, elec service, asphalt | G17: 1197367.3 | H17: 300000 | I17: =+G17-H17 -> 897367.29 | J17: 0 | K17: =+I17+J17 -> 897367.29 | L17: =+K17/$K$190 -> 0.064558798 | M17: =+K17/$T$9 -> 10.913292 | N17: =+K17-SUM(O17:AL17) -> 611850.35 | O17: =115016.94-5283.3 -> 109733.64 | P17: 0 | Q17: 161975 | R17: 0 | S17: 0 | T17: 0 | U17: 0 | V17: 0 | W17: 0 | X17: 0 | Y17: 0 | Z17: 0 | AA17: 0 | AB17: 0 | AC17: 0 | AD17: 0 | AE17: 0 | AF17: 0 | AG17: 0 | AH17: 0 | AI17: 0 | AJ17: 0 | AK17: 0 | AL17: 13808.3 | AM17: =SUM(O17:AL17) -> 285516.94 | AN17: =IF(K17=0,"",(K17-N17-AL17)/K17) -> 0.3027842
A18: =IFERROR(VLOOKUP(C18,'Product List'!$A$2:$C198,2,FALSE),"") | B18: =IFERROR(VLOOKUP(C18,'Product List'!$A$2:$C198,3,FALSE),"") | E18: =+E17+1 -> 3 | F18: Footings & Foundations M&L & site M&L | G18: 408552 | H18: 216541.42 | I18: =+G18-H18 -> 192010.58 | J18: 0 | K18: =+I18+J18 -> 192010.58 | L18: =+K18/$K$190 -> 0.013813711 | M18: =+K18/$T$9 -> 2.3351281 | N18: =+K18-SUM(O18:AL18) -> 177823.67 | O18: 7268.96 | P18: 0 | Q18: 2457.93 | R18: 0 | S18: 0 | T18: 0 | U18: 0 | V18: 0 | W18: 0 | X18: 0 | Y18: 0 | Z18: 0 | AA18: 0 | AB18: 0 | AC18: 0 | AD18: 0 | AE18: 0 | AF18: 0 | AG18: 0 | AH18: 0 | AI18: 0 | AJ18: 0 | AK18: 0 | AL18: 4460.02 | AM18: =SUM(O18:AL18) -> 14186.91 | AN18: =IF(K18=0,"",(K18-N18-AL18)/K18) -> 0.050658094
A19: =IFERROR(VLOOKUP(C19,'Product List'!$A$2:$C198,2,FALSE),"") | B19: =IFERROR(VLOOKUP(C19,'Product List'!$A$2:$C198,3,FALSE),"") | E19: =+E18+1 -> 4 | F19: ALL FENCING | G19: 44475 | H19: 0 | I19: =+G19-H19 -> 44475 | J19: 0 | K19: =+I19+J19 -> 44475 | L19: =+K19/$K$190 -> 0.0031996403 | M19: =+K19/$T$9 -> 0.54088073 | N19: =+K19-SUM(O19:AL19) -> 44475 | O19: 0 | P19: 0 | Q19: 0 | R19: 0 | S19: 0 | T19: 0 | U19: 0 | V19: 0 | W19: 0 | X19: 0 | Y19: 0 | Z19: 0 | AA19: 0 | AB19: 0 | AC19: 0 | AD19: 0 | AE19: 0 | AF19: 0 | AG19: 0 | AH19: 0 | AI19: 0 | AJ19: 0 | AK19: 0 | AM19: =SUM(O19:AL19) -> 0 | AN19: =IF(K19=0,"",(K19-N19-AL19)/K19) -> 0
A20: =IFERROR(VLOOKUP(C20,'Product List'!$A$2:$C198,2,FALSE),"") | B20: =IFERROR(VLOOKUP(C20,'Product List'!$A$2:$C198,3,FALSE),"") | E20: =+E19+1 -> 5 | F20: TURNKEY FRAMING, | G20: 2063122 | H20: 100000 | I20: =+G20-H20 -> 1963122 | J20: 0 | K20: =+I20+J20 -> 1963122 | L20: =+K20/$K$190 -> 0.1412318 | M20: =+K20/$T$9 -> 23.874421 | N20: =+K20-SUM(O20:AL20) -> 389153.62 | O20: =504946-25247.3 -> 479698.7 | P20: =820034-41001.7 -> 779032.3 | Q20: 236538.97 | R20: 0 | S20: 0 | T20: 0 | U20: 0 | V20: 0 | W20: 0 | X20: 0 | Y20: 0 | Z20: 0 | AA20: 0 | AB20: 0 | AC20: 0 | AD20: 0 | AE20: 0 | AF20: 0 | AG20: 0 | AH20: 0 | AI20: 0 | AJ20: 0 | AK20: 0 | AL20: 78698.41 | AM20: =SUM(O20:AL20) -> 1573968.4 | AN20: =IF(K20=0,"",(K20-N20-AL20)/K20) -> 0.7616796
A21: =IFERROR(VLOOKUP(C21,'Product List'!$A$2:$C198,2,FALSE),"") | B21: =IFERROR(VLOOKUP(C21,'Product List'!$A$2:$C198,3,FALSE),"") | E21: =+E20+1 -> 6 | F21: Roofing Labor and Materials | G21: 235254.4 | H21: 0 | I21: =+G21-H21 -> 235254.4 | J21: 0 | K21: =+I21+J21 -> 235254.4 | L21: =+K21/$K$190 -> 0.016924777 | M21: =+K21/$T$9 -> 2.8610359 | N21: =+K21-SUM(O21:AL21) -> 235254.4 | O21: 0 | P21: 0 | Q21: 0 | R21: 0 | S21: 0 | T21: 0 | U21: 0 | V21: 0 | W21: 0 | X21: 0 | Y21: 0 | Z21: 0 | AA21: 0 | AB21: 0 | AC21: 0 | AD21: 0 | AE21: 0 | AF21: 0 | AG21: 0 | AH21: 0 | AI21: 0 | AJ21: 0 | AK21: 0 | AM21: =SUM(O21:AL21) -> 0 | AN21: =IF(K21=0,"",(K21-N21-AL21)/K21) -> 0
A22: =IFERROR(VLOOKUP(C22,'Product List'!$A$2:$C198,2,FALSE),"") | B22: =IFERROR(VLOOKUP(C22,'Product List'!$A$2:$C198,3,FALSE),"") | E22: =+E21+1 -> 7 | F22: DECK COATINGS | G22: 72445 | H22: 0 | I22: =+G22-H22 -> 72445 | J22: 0 | K22: =+I22+J22 -> 72445 | L22: =+K22/$K$190 -> 0.0052118705 | M22: =+K22/$T$9 -> 0.88103664 | N22: =+K22-SUM(O22:AL22) -> 72445 | O22: 0 | P22: 0 | Q22: 0 | R22: 0 | S22: 0 | T22: 0 | U22: 0 | V22: 0 | W22: 0 | X22: 0 | Y22: 0 | Z22: 0 | AA22: 0 | AB22: 0 | AC22: 0 | AD22: 0 | AE22: 0 | AF22: 0 | AG22: 0 | AH22: 0 | AI22: 0 | AJ22: 0 | AK22: 0 | AM22: =SUM(O22:AL22) -> 0 | AN22: =IF(K22=0,"",(K22-N22-AL22)/K22) -> 0
A23: =IFERROR(VLOOKUP(C23,'Product List'!$A$2:$C198,2,FALSE),"") | B23: =IFERROR(VLOOKUP(C23,'Product List'!$A$2:$C198,3,FALSE),"") | E23: =+E22+1 -> 8 | F23: Structural steel (Covered parking) | G23: 35813.74 | H23: 0 | I23: =+G23-H23 -> 35813.74 | J23: 0 | K23: =+I23+J23 -> 35813.74 | L23: =+K23/$K$190 -> 0.0025765281 | M23: =+K23/$T$9 -> 0.4355472 | N23: =+K23-SUM(O23:AL23) -> 35813.74 | O23: 0 | P23: 0 | Q23: 0 | R23: 0 | S23: 0 | T23: 0 | U23: 0 | V23: 0 | W23: 0 | X23: 0 | Y23: 0 | Z23: 0 | AA23: 0 | AB23: 0 | AC23: 0 | AD23: 0 | AE23: 0 | AF23: 0 | AG23: 0 | AH23: 0 | AI23: 0 | AJ23: 0 | AK23: 0 | AM23: =SUM(O23:AL23) -> 0 | AN23: =IF(K23=0,"",(K23-N23-AL23)/K23) -> 0
A24: =IFERROR(VLOOKUP(C24,'Product List'!$A$2:$C198,2,FALSE),"") | B24: =IFERROR(VLOOKUP(C24,'Product List'!$A$2:$C198,3,FALSE),"") | E24: =+E23+1 -> 9 | F24: ALL OTHER STEEL FEATURES | G24: 196050 | H24: 0 | I24: =+G24-H24 -> 196050 | J24: 0 | K24: =+I24+J24 -> 196050 | L24: =+K24/$K$190 -> 0.014104317 | M24: =+K24/$T$9 -> 2.3842533 | N24: =+K24-SUM(O24:AL24) -> 196050 | O24: 0 | P24: 0 | Q24: 0 | R24: 0 | S24: 0 | T24: 0 | U24: 0 | V24: 0 | W24: 0 | X24: 0 | Y24: 0 | Z24: 0 | AA24: 0 | AB24: 0 | AC24: 0 | AD24: 0 | AE24: 0 | AF24: 0 | AG24: 0 | AH24: 0 | AI24: 0 | AJ24: 0 | AK24: 0 | AM24: =SUM(O24:AL24) -> 0 | AN24: =IF(K24=0,"",(K24-N24-AL24)/K24) -> 0
A25: =IFERROR(VLOOKUP(C25,'Product List'!$A$2:$C198,2,FALSE),"") | B25: =IFERROR(VLOOKUP(C25,'Product List'!$A$2:$C198,3,FALSE),"") | E25: =+E24+1 -> 10 | F25: Windows | G25: 170000 | H25: 0 | I25: =+G25-H25 -> 170000 | J25: 0 | K25: =+I25+J25 -> 170000 | L25: =+K25/$K$190 -> 0.012230216 | M25: =+K25/$T$9 -> 2.0674474 | N25: =+K25-SUM(O25:AL25) -> 170000 | O25: 0 | P25: 0 | Q25: 0 | R25: 0 | S25: 0 | T25: 0 | U25: 0 | V25: 0 | W25: 0 | X25: 0 | Y25: 0 | Z25: 0 | AA25: 0 | AB25: 0 | AC25: 0 | AD25: 0 | AE25: 0 | AF25: 0 | AG25: 0 | AH25: 0 | AI25: 0 | AJ25: 0 | AK25: 0 | AM25: =SUM(O25:AL25) -> 0 | AN25: =IF(K25=0,"",(K25-N25-AL25)/K25) -> 0
A26: =IFERROR(VLOOKUP(C26,'Product List'!$A$2:$C198,2,FALSE),"") | B26: =IFERROR(VLOOKUP(C26,'Product List'!$A$2:$C198,3,FALSE),"") | E26: =+E25+1 -> 11 | F26: Store Front L&M | G26: 95488 | H26: 0 | I26: =+G26-H26 -> 95488 | J26: 0 | K26: =+I26+J26 -> 95488 | L26: =+K26/$K$190 -> 0.0068696403 | M26: =+K26/$T$9 -> 1.1612731 | N26: =+K26-SUM(O26:AL26) -> 95488 | O26: 0 | P26: 0 | Q26: 0 | R26: 0 | S26: 0 | T26: 0 | U26: 0 | V26: 0 | W26: 0 | X26: 0 | Y26: 0 | Z26: 0 | AA26: 0 | AB26: 0 | AC26: 0 | AD26: 0 | AE26: 0 | AF26: 0 | AG26: 0 | AH26: 0 | AI26: 0 | AJ26: 0 | AK26: 0 | AM26: =SUM(O26:AL26) -> 0 | AN26: =IF(K26=0,"",(K26-N26-AL26)/K26) -> 0
A27: =IFERROR(VLOOKUP(C27,'Product List'!$A$2:$C198,2,FALSE),"") | B27: =IFERROR(VLOOKUP(C27,'Product List'!$A$2:$C198,3,FALSE),"") | E27: =+E26+1 -> 12 | F27: ELEVATOR | G27: 255500 | H27: 0 | I27: =+G27-H27 -> 255500 | J27: 0 | K27: =+I27+J27 -> 255500 | L27: =+K27/$K$190 -> 0.018381295 | M27: =+K27/$T$9 -> 3.1072519 | N27: =+K27-SUM(O27:AL27) -> 255500 | O27: 0 | P27: 0 | Q27: 0 | R27: 0 | S27: 0 | T27: 0 | U27: 0 | V27: 0 | W27: 0 | X27: 0 | Y27: 0 | Z27: 0 | AA27: 0 | AB27: 0 | AC27: 0 | AD27: 0 | AE27: 0 | AF27: 0 | AG27: 0 | AH27: 0 | AI27: 0 | AJ27: 0 | AK27: 0 | AM27: =SUM(O27:AL27) -> 0 | AN27: =IF(K27=0,"",(K27-N27-AL27)/K27) -> 0
A28: =IFERROR(VLOOKUP(C28,'Product List'!$A$2:$C198,2,FALSE),"") | B28: =IFERROR(VLOOKUP(C28,'Product List'!$A$2:$C198,3,FALSE),"") | E28: =+E27+1 -> 13 | F28: HM door labor | G28: 18575 | H28: 0 | I28: =+G28-H28 -> 18575 | J28: 0 | K28: =+I28+J28 -> 18575 | L28: =+K28/$K$190 -> 0.0013363309 | M28: =+K28/$T$9 -> 0.22589904 | N28: =+K28-SUM(O28:AL28) -> 18575 | O28: 0 | P28: 0 | Q28: 0 | R28: 0 | S28: 0 | T28: 0 | U28: 0 | V28: 0 | W28: 0 | X28: 0 | Y28: 0 | Z28: 0 | AA28: 0 | AB28: 0 | AC28: 0 | AD28: 0 | AE28: 0 | AF28: 0 | AG28: 0 | AH28: 0 | AI28: 0 | AJ28: 0 | AK28: 0 | AM28: =SUM(O28:AL28) -> 0 | AN28: =IF(K28=0,"",(K28-N28-AL28)/K28) -> 0
A29: =IFERROR(VLOOKUP(C29,'Product List'!$A$2:$C198,2,FALSE),"") | B29: =IFERROR(VLOOKUP(C29,'Product List'!$A$2:$C198,3,FALSE),"") | E29: =+E28+1 -> 14 | F29: Plumbing | G29: 1125000 | H29: 338750 | I29: =+G29-H29 -> 786250 | J29: 0 | K29: =+I29+J29 -> 786250 | L29: =+K29/$K$190 -> 0.056564748 | M29: =+K29/$T$9 -> 9.5619444 | N29: =+K29-SUM(O29:AL29) -> 600000 | O29: 0 | P29: =62500-3125 -> 59375 | Q29: 106875 | R29: 0 | S29: 0 | T29: 0 | U29: 0 | V29: 0 | W29: 0 | X29: 0 | Y29: 0 | Z29: 0 | AA29: 0 | AB29: 0 | AC29: 0 | AD29: 0 | AE29: 0 | AF29: 0 | AG29: 0 | AH29: 0 | AI29: 0 | AJ29: 0 | AK29: 0 | AL29: 20000 | AM29: =SUM(O29:AL29) -> 186250 | AN29: =IF(K29=0,"",(K29-N29-AL29)/K29) -> 0.21144674
A30: =IFERROR(VLOOKUP(C30,'Product List'!$A$2:$C198,2,FALSE),"") | B30: =IFERROR(VLOOKUP(C30,'Product List'!$A$2:$C198,3,FALSE),"") | E30: =+E29+1 -> 15 | F30: HVAC | G30: 1395000 | H30: 150000 | I30: =+G30-H30 -> 1245000 | J30: 0 | K30: =+I30+J30 -> 1245000 | L30: =+K30/$K$190 -> 0.089568345 | M30: =+K30/$T$9 -> 15.141012 | N30: =+K30-SUM(O30:AL30) -> 1125000 | O30: 0 | P30: 0 | Q30: 114000 | R30: 0 | S30: 0 | T30: 0 | U30: 0 | V30: 0 | W30: 0 | X30: 0 | Y30: 0 | Z30: 0 | AA30: 0 | AB30: 0 | AC30: 0 | AD30: 0 | AE30: 0 | AF30: 0 | AG30: 0 | AH30: 0 | AI30: 0 | AJ30: 0 | AK30: 0 | AL30: 6000 | AM30: =SUM(O30:AL30) -> 120000 | AN30: =IF(K30=0,"",(K30-N30-AL30)/K30) -> 0.091566265
A31: =IFERROR(VLOOKUP(C31,'Product List'!$A$2:$C198,2,FALSE),"") | B31: =IFERROR(VLOOKUP(C31,'Product List'!$A$2:$C198,3,FALSE),"") | E31: =+E30+1 -> 16 | F31: Electric | G31: 1186352 | H31: 400000 | I31: =+G31-H31 -> 786352 | J31: 0 | K31: =+I31+J31 -> 786352 | L31: =+K31/$K$190 -> 0.056572086 | M31: =+K31/$T$9 -> 9.5631848 | N31: =+K31-SUM(O31:AL31) -> 786352 | O31: 0 | P31: 0 | Q31: 0 | R31: 0 | S31: 0 | T31: 0 | U31: 0 | V31: 0 | W31: 0 | X31: 0 | Y31: 0 | Z31: 0 | AA31: 0 | AB31: 0 | AC31: 0 | AD31: 0 | AE31: 0 | AF31: 0 | AG31: 0 | AH31: 0 | AI31: 0 | AJ31: 0 | AK31: 0 | AM31: =SUM(O31:AL31) -> 0 | AN31: =IF(K31=0,"",(K31-N31-AL31)/K31) -> 0
A32: =IFERROR(VLOOKUP(C32,'Product List'!$A$2:$C198,2,FALSE),"") | B32: =IFERROR(VLOOKUP(C32,'Product List'!$A$2:$C198,3,FALSE),"") | E32: =+E31+1 -> 17 | F32: SPRINKLER SYSTEM | G32: 156271 | H32: 0 | I32: =+G32-H32 -> 156271 | J32: 0 | K32: =+I32+J32 -> 156271 | L32: =+K32/$K$190 -> 0.011242518 | M32: =+K32/$T$9 -> 1.9004828 | N32: =+K32-SUM(O32:AL32) -> 156271 | O32: 0 | P32: 0 | Q32: 0 | R32: 0 | S32: 0 | T32: 0 | U32: 0 | V32: 0 | W32: 0 | X32: 0 | Y32: 0 | Z32: 0 | AA32: 0 | AB32: 0 | AC32: 0 | AD32: 0 | AE32: 0 | AF32: 0 | AG32: 0 | AH32: 0 | AI32: 0 | AJ32: 0 | AK32: 0 | AM32: =SUM(O32:AL32) -> 0 | AN32: =IF(K32=0,"",(K32-N32-AL32)/K32) -> 0
A33: =IFERROR(VLOOKUP(C33,'Product List'!$A$2:$C198,2,FALSE),"") | B33: =IFERROR(VLOOKUP(C33,'Product List'!$A$2:$C198,3,FALSE),"") | E33: =+E32+1 -> 18 | F33: FIRE CAULKING | G33: 10000 | H33: 0 | I33: =+G33-H33 -> 10000 | J33: 0 | K33: =+I33+J33 -> 10000 | L33: =+K33/$K$190 -> 0.00071942446 | M33: =+K33/$T$9 -> 0.12161455 | N33: =+K33-SUM(O33:AL33) -> 10000 | O33: 0 | P33: 0 | Q33: 0 | R33: 0 | S33: 0 | T33: 0 | U33: 0 | V33: 0 | W33: 0 | X33: 0 | Y33: 0 | Z33: 0 | AA33: 0 | AB33: 0 | AC33: 0 | AD33: 0 | AE33: 0 | AF33: 0 | AG33: 0 | AH33: 0 | AI33: 0 | AJ33: 0 | AK33: 0 | AM33: =SUM(O33:AL33) -> 0 | AN33: =IF(K33=0,"",(K33-N33-AL33)/K33) -> 0
A34: =IFERROR(VLOOKUP(C34,'Product List'!$A$2:$C198,2,FALSE),"") | B34: =IFERROR(VLOOKUP(C34,'Product List'!$A$2:$C198,3,FALSE),"") | E34: =+E33+1 -> 19 | F34: GYPCRETE | G34: 77757.03 | H34: 0 | I34: =+G34-H34 -> 77757.03 | J34: 0 | K34: =+I34+J34 -> 77757.03 | L34: =+K34/$K$190 -> 0.0055940309 | M34: =+K34/$T$9 -> 0.94563866 | N34: =+K34-SUM(O34:AL34) -> 77757.03 | O34: 0 | P34: 0 | Q34: 0 | R34: 0 | S34: 0 | T34: 0 | U34: 0 | V34: 0 | W34: 0 | X34: 0 | Y34: 0 | Z34: 0 | AA34: 0 | AB34: 0 | AC34: 0 | AD34: 0 | AE34: 0 | AF34: 0 | AG34: 0 | AH34: 0 | AI34: 0 | AJ34: 0 | AK34: 0 | AM34: =SUM(O34:AL34) -> 0 | AN34: =IF(K34=0,"",(K34-N34-AL34)/K34) -> 0
A35: =IFERROR(VLOOKUP(C35,'Product List'!$A$2:$C198,2,FALSE),"") | B35: =IFERROR(VLOOKUP(C35,'Product List'!$A$2:$C198,3,FALSE),"") | E35: =+E34+1 -> 20 | F35: Insulation | G35: 232552 | H35: 2600.62 | I35: =+G35-H35 -> 229951.38 | J35: 0 | K35: =+I35+J35 -> 229951.38 | L35: =+K35/$K$190 -> 0.016543265 | M35: =+K35/$T$9 -> 2.7965435 | N35: =+K35-SUM(O35:AL35) -> 229814.5 | O35: 0 | P35: 0 | Q35: 0 | R35: 0 | S35: 0 | T35: 0 | U35: 0 | V35: 0 | W35: 0 | X35: 0 | Y35: 0 | Z35: 0 | AA35: 0 | AB35: 0 | AC35: 0 | AD35: 0 | AE35: 0 | AF35: 0 | AG35: 0 | AH35: 0 | AI35: 0 | AJ35: 0 | AK35: 0 | AL35: 136.88 | AM35: =SUM(O35:AL35) -> 136.88 | AN35: =IF(K35=0,"",(K35-N35-AL35)/K35) -> 0
A36: =IFERROR(VLOOKUP(C36,'Product List'!$A$2:$C198,2,FALSE),"") | B36: =IFERROR(VLOOKUP(C36,'Product List'!$A$2:$C198,3,FALSE),"") | E36: =+E35+1 -> 21 | F36: Sheetrock | G36: 850750 | H36: 0 | I36: =+G36-H36 -> 850750 | J36: 0 | K36: =+I36+J36 -> 850750 | L36: =+K36/$K$190 -> 0.061205036 | M36: =+K36/$T$9 -> 10.346358 | N36: =+K36-SUM(O36:AL36) -> 850750 | O36: 0 | P36: 0 | Q36: 0 | R36: 0 | S36: 0 | T36: 0 | U36: 0 | V36: 0 | W36: 0 | X36: 0 | Y36: 0 | Z36: 0 | AA36: 0 | AB36: 0 | AC36: 0 | AD36: 0 | AE36: 0 | AF36: 0 | AG36: 0 | AH36: 0 | AI36: 0 | AJ36: 0 | AK36: 0 | AM36: =SUM(O36:AL36) -> 0 | AN36: =IF(K36=0,"",(K36-N36-AL36)/K36) -> 0
A37: =IFERROR(VLOOKUP(C37,'Product List'!$A$2:$C198,2,FALSE),"") | B37: =IFERROR(VLOOKUP(C37,'Product List'!$A$2:$C198,3,FALSE),"") | E37: =+E36+1 -> 22 | F37: 2 layers of dens glass | G37: 120000 | H37: 0 | I37: =+G37-H37 -> 120000 | J37: 0 | K37: =+I37+J37 -> 120000 | L37: =+K37/$K$190 -> 0.0086330935 | M37: =+K37/$T$9 -> 1.4593747 | N37: =+K37-SUM(O37:AL37) -> 120000 | O37: 0 | P37: 0 | Q37: 0 | R37: 0 | S37: 0 | T37: 0 | U37: 0 | V37: 0 | W37: 0 | X37: 0 | Y37: 0 | Z37: 0 | AA37: 0 | AB37: 0 | AC37: 0 | AD37: 0 | AE37: 0 | AF37: 0 | AG37: 0 | AH37: 0 | AI37: 0 | AJ37: 0 | AK37: 0 | AM37: =SUM(O37:AL37) -> 0 | AN37: =IF(K37=0,"",(K37-N37-AL37)/K37) -> 0
A38: =IFERROR(VLOOKUP(C38,'Product List'!$A$2:$C198,2,FALSE),"") | B38: =IFERROR(VLOOKUP(C38,'Product List'!$A$2:$C198,3,FALSE),"") | E38: =+E37+1 -> 23 | F38: FINISH MATERIALS MISC | G38: 325000 | H38: 0 | I38: =+G38-H38 -> 325000 | J38: 0 | K38: =+I38+J38 -> 325000 | L38: =+K38/$K$190 -> 0.023381295 | M38: =+K38/$T$9 -> 3.952473 | N38: =+K38-SUM(O38:AL38) -> 325000 | O38: 0 | P38: 0 | Q38: 0 | R38: 0 | S38: 0 | T38: 0 | U38: 0 | V38: 0 | W38: 0 | X38: 0 | Y38: 0 | Z38: 0 | AA38: 0 | AB38: 0 | AC38: 0 | AD38: 0 | AE38: 0 | AF38: 0 | AG38: 0 | AH38: 0 | AI38: 0 | AJ38: 0 | AK38: 0 | AM38: =SUM(O38:AL38) -> 0 | AN38: =IF(K38=0,"",(K38-N38-AL38)/K38) -> 0
A39: =IFERROR(VLOOKUP(C39,'Product List'!$A$2:$C198,2,FALSE),"") | B39: =IFERROR(VLOOKUP(C39,'Product List'!$A$2:$C198,3,FALSE),"") | E39: =+E38+1 -> 24 | F39: Finish Labor | G39: 95000 | H39: 0 | I39: =+G39-H39 -> 95000 | J39: 0 | K39: =+I39+J39 -> 95000 | L39: =+K39/$K$190 -> 0.0068345324 | M39: =+K39/$T$9 -> 1.1553383 | N39: =+K39-SUM(O39:AL39) -> 95000 | O39: 0 | P39: 0 | Q39: 0 | R39: 0 | S39: 0 | T39: 0 | U39: 0 | V39: 0 | W39: 0 | X39: 0 | Y39: 0 | Z39: 0 | AA39: 0 | AB39: 0 | AC39: 0 | AD39: 0 | AE39: 0 | AF39: 0 | AG39: 0 | AH39: 0 | AI39: 0 | AJ39: 0 | AK39: 0 | AM39: =SUM(O39:AL39) -> 0 | AN39: =IF(K39=0,"",(K39-N39-AL39)/K39) -> 0
A40: =IFERROR(VLOOKUP(C40,'Product List'!$A$2:$C198,2,FALSE),"") | B40: =IFERROR(VLOOKUP(C40,'Product List'!$A$2:$C198,3,FALSE),"") | E40: =+E39+1 -> 25 | F40: Interior Paint | G40: 213852.35 | H40: 213852.35 | I40: =+G40-H40 -> 0 | J40: 0 | K40: =+I40+J40 -> 0 | L40: =+K40/$K$190 -> 0 | M40: =+K40/$T$9 -> 0 | N40: =+K40-SUM(O40:AL40) -> 0 | O40: 0 | P40: 0 | Q40: 0 | R40: 0 | S40: 0 | T40: 0 | U40: 0 | V40: 0 | W40: 0 | X40: 0 | Y40: 0 | Z40: 0 | AA40: 0 | AB40: 0 | AC40: 0 | AD40: 0 | AE40: 0 | AF40: 0 | AG40: 0 | AH40: 0 | AI40: 0 | AJ40: 0 | AK40: 0 | AM40: =SUM(O40:AL40) -> 0 | AN40: =IF(K40=0,"",(K40-N40-AL40)/K40)
A41: =IFERROR(VLOOKUP(C41,'Product List'!$A$2:$C198,2,FALSE),"") | B41: =IFERROR(VLOOKUP(C41,'Product List'!$A$2:$C198,3,FALSE),"") | E41: =+E40+1 -> 26 | F41: CABINETS | G41: 461324.15 | H41: 261324.15 | I41: =+G41-H41 -> 200000 | J41: 0 | K41: =+I41+J41 -> 200000 | L41: =+K41/$K$190 -> 0.014388489 | M41: =+K41/$T$9 -> 2.4322911 | N41: =+K41-SUM(O41:AL41) -> 200000 | O41: 0 | P41: 0 | Q41: 0 | R41: 0 | S41: 0 | T41: 0 | U41: 0 | V41: 0 | W41: 0 | X41: 0 | Y41: 0 | Z41: 0 | AA41: 0 | AB41: 0 | AC41: 0 | AD41: 0 | AE41: 0 | AF41: 0 | AG41: 0 | AH41: 0 | AI41: 0 | AJ41: 0 | AK41: 0 | AM41: =SUM(O41:AL41) -> 0 | AN41: =IF(K41=0,"",(K41-N41-AL41)/K41) -> 0
A42: =IFERROR(VLOOKUP(C42,'Product List'!$A$2:$C198,2,FALSE),"") | B42: =IFERROR(VLOOKUP(C42,'Product List'!$A$2:$C198,3,FALSE),"") | E42: =+E41+1 -> 27 | F42: EQUIPMENT FOR CABINETS | G42: 6000 | H42: 0 | I42: =+G42-H42 -> 6000 | J42: 0 | K42: =+I42+J42 -> 6000 | L42: =+K42/$K$190 -> 0.00043165468 | M42: =+K42/$T$9 -> 0.072968733 | N42: =+K42-SUM(O42:AL42) -> 6000 | O42: 0 | P42: 0 | Q42: 0 | R42: 0 | S42: 0 | T42: 0 | U42: 0 | V42: 0 | W42: 0 | X42: 0 | Y42: 0 | Z42: 0 | AA42: 0 | AB42: 0 | AC42: 0 | AD42: 0 | AE42: 0 | AF42: 0 | AG42: 0 | AH42: 0 | AI42: 0 | AJ42: 0 | AK42: 0 | AM42: =SUM(O42:AL42) -> 0 | AN42: =IF(K42=0,"",(K42-N42-AL42)/K42) -> 0
A43: =IFERROR(VLOOKUP(C43,'Product List'!$A$2:$C198,2,FALSE),"") | B43: =IFERROR(VLOOKUP(C43,'Product List'!$A$2:$C198,3,FALSE),"") | E43: =+E42+1 -> 28 | F43: unit entry doors | G43: 125000 | H43: 0 | I43: =+G43-H43 -> 125000 | J43: 0 | K43: =+I43+J43 -> 125000 | L43: =+K43/$K$190 -> 0.0089928058 | M43: =+K43/$T$9 -> 1.5201819 | N43: =+K43-SUM(O43:AL43) -> 125000 | O43: 0 | P43: 0 | Q43: 0 | R43: 0 | S43: 0 | T43: 0 | U43: 0 | V43: 0 | W43: 0 | X43: 0 | Y43: 0 | Z43: 0 | AA43: 0 | AB43: 0 | AC43: 0 | AD43: 0 | AE43: 0 | AF43: 0 | AG43: 0 | AH43: 0 | AI43: 0 | AJ43: 0 | AK43: 0 | AM43: =SUM(O43:AL43) -> 0 | AN43: =IF(K43=0,"",(K43-N43-AL43)/K43) -> 0
A44: =IFERROR(VLOOKUP(C44,'Product List'!$A$2:$C198,2,FALSE),"") | B44: =IFERROR(VLOOKUP(C44,'Product List'!$A$2:$C198,3,FALSE),"") | E44: =+E43+1 -> 29 | F44: FLOOR PREP | G44: 10000 | H44: 0 | I44: =+G44-H44 -> 10000 | J44: 0 | K44: =+I44+J44 -> 10000 | L44: =+K44/$K$190 -> 0.00071942446 | M44: =+K44/$T$9 -> 0.12161455 | N44: =+K44-SUM(O44:AL44) -> 10000 | O44: 0 | P44: 0 | Q44: 0 | R44: 0 | S44: 0 | T44: 0 | U44: 0 | V44: 0 | W44: 0 | X44: 0 | Y44: 0 | Z44: 0 | AA44: 0 | AB44: 0 | AC44: 0 | AD44: 0 | AE44: 0 | AF44: 0 | AG44: 0 | AH44: 0 | AI44: 0 | AJ44: 0 | AK44: 0 | AM44: =SUM(O44:AL44) -> 0 | AN44: =IF(K44=0,"",(K44-N44-AL44)/K44) -> 0
A45: =IFERROR(VLOOKUP(C45,'Product List'!$A$2:$C198,2,FALSE),"") | B45: =IFERROR(VLOOKUP(C45,'Product List'!$A$2:$C198,3,FALSE),"") | E45: =+E44+1 -> 30 | F45: Hardware labor | G45: 47550 | H45: 0 | I45: =+G45-H45 -> 47550 | J45: 0 | K45: =+I45+J45 -> 47550 | L45: =+K45/$K$190 -> 0.0034208633 | M45: =+K45/$T$9 -> 0.57827721 | N45: =+K45-SUM(O45:AL45) -> 47550 | O45: 0 | P45: 0 | Q45: 0 | R45: 0 | S45: 0 | T45: 0 | U45: 0 | V45: 0 | W45: 0 | X45: 0 | Y45: 0 | Z45: 0 | AA45: 0 | AB45: 0 | AC45: 0 | AD45: 0 | AE45: 0 | AF45: 0 | AG45: 0 | AH45: 0 | AI45: 0 | AJ45: 0 | AK45: 0 | AM45: =SUM(O45:AL45) -> 0 | AN45: =IF(K45=0,"",(K45-N45-AL45)/K45) -> 0
A46: =IFERROR(VLOOKUP(C46,'Product List'!$A$2:$C198,2,FALSE),"") | B46: =IFERROR(VLOOKUP(C46,'Product List'!$A$2:$C198,3,FALSE),"") | E46: =+E45+1 -> 31 | F46: Hardware & HM frames & doors | G46: 58110.22 | H46: 0 | I46: =+G46-H46 -> 58110.22 | J46: 0 | K46: =+I46+J46 -> 58110.22 | L46: =+K46/$K$190 -> 0.0041805914 | M46: =+K46/$T$9 -> 0.70670485 | N46: =+K46-SUM(O46:AL46) -> 58110.22 | O46: 0 | P46: 0 | Q46: 0 | R46: 0 | S46: 0 | T46: 0 | U46: 0 | V46: 0 | W46: 0 | X46: 0 | Y46: 0 | Z46: 0 | AA46: 0 | AB46: 0 | AC46: 0 | AD46: 0 | AE46: 0 | AF46: 0 | AG46: 0 | AH46: 0 | AI46: 0 | AJ46: 0 | AK46: 0 | AM46: =SUM(O46:AL46) -> 0 | AN46: =IF(K46=0,"",(K46-N46-AL46)/K46) -> 0
A47: =IFERROR(VLOOKUP(C47,'Product List'!$A$2:$C198,2,FALSE),"") | B47: =IFERROR(VLOOKUP(C47,'Product List'!$A$2:$C198,3,FALSE),"") | E47: =+E46+1 -> 32 | F47: FIRE EXTINGUSHERS | G47: 7850 | H47: 0 | I47: =+G47-H47 -> 7850 | J47: 0 | K47: =+I47+J47 -> 7850 | L47: =+K47/$K$190 -> 0.0005647482 | M47: =+K47/$T$9 -> 0.095467426 | N47: =+K47-SUM(O47:AL47) -> 7850 | O47: 0 | P47: 0 | Q47: 0 | R47: 0 | S47: 0 | T47: 0 | U47: 0 | V47: 0 | W47: 0 | X47: 0 | Y47: 0 | Z47: 0 | AA47: 0 | AB47: 0 | AC47: 0 | AD47: 0 | AE47: 0 | AF47: 0 | AG47: 0 | AH47: 0 | AI47: 0 | AJ47: 0 | AK47: 0 | AM47: =SUM(O47:AL47) -> 0 | AN47: =IF(K47=0,"",(K47-N47-AL47)/K47) -> 0
A48: =IFERROR(VLOOKUP(C48,'Product List'!$A$2:$C198,2,FALSE),"") | B48: =IFERROR(VLOOKUP(C48,'Product List'!$A$2:$C198,3,FALSE),"") | E48: =+E47+1 -> 33 | F48: MIRRORS | G48: 34000 | H48: 0 | I48: =+G48-H48 -> 34000 | J48: 0 | K48: =+I48+J48 -> 34000 | L48: =+K48/$K$190 -> 0.0024460432 | M48: =+K48/$T$9 -> 0.41348949 | N48: =+K48-SUM(O48:AL48) -> 34000 | O48: 0 | P48: 0 | Q48: 0 | R48: 0 | S48: 0 | T48: 0 | U48: 0 | V48: 0 | W48: 0 | X48: 0 | Y48: 0 | Z48: 0 | AA48: 0 | AB48: 0 | AC48: 0 | AD48: 0 | AE48: 0 | AF48: 0 | AG48: 0 | AH48: 0 | AI48: 0 | AJ48: 0 | AK48: 0 | AM48: =SUM(O48:AL48) -> 0 | AN48: =IF(K48=0,"",(K48-N48-AL48)/K48) -> 0
A49: =IFERROR(VLOOKUP(C49,'Product List'!$A$2:$C198,2,FALSE),"") | B49: =IFERROR(VLOOKUP(C49,'Product List'!$A$2:$C198,3,FALSE),"") | E49: =+E48+1 -> 34 | F49: All flooring & wall tile M&L | G49: 312858 | H49: 0 | I49: =+G49-H49 -> 312858 | J49: 0 | K49: =+I49+J49 -> 312858 | L49: =+K49/$K$190 -> 0.02250777 | M49: =+K49/$T$9 -> 3.8048086 | N49: =+K49-SUM(O49:AL49) -> 312858 | O49: 0 | P49: 0 | Q49: 0 | R49: 0 | S49: 0 | T49: 0 | U49: 0 | V49: 0 | W49: 0 | X49: 0 | Y49: 0 | Z49: 0 | AA49: 0 | AB49: 0 | AC49: 0 | AD49: 0 | AE49: 0 | AF49: 0 | AG49: 0 | AH49: 0 | AI49: 0 | AJ49: 0 | AK49: 0 | AM49: =SUM(O49:AL49) -> 0 | AN49: =IF(K49=0,"",(K49-N49-AL49)/K49) -> 0
A50: =IFERROR(VLOOKUP(C50,'Product List'!$A$2:$C198,2,FALSE),"") | B50: =IFERROR(VLOOKUP(C50,'Product List'!$A$2:$C198,3,FALSE),"") | E50: =+E49+1 -> 35 | F50: Brick, Stucco, Soffit & fascia | G50: 748952 | H50: 0 | I50: =+G50-H50 -> 748952 | J50: 0 | K50: =+I50+J50 -> 748952 | L50: =+K50/$K$190 -> 0.053881439 | M50: =+K50/$T$9 -> 9.1083464 | N50: =+K50-SUM(O50:AL50) -> 748952 | O50: 0 | P50: 0 | Q50: 0 | R50: 0 | S50: 0 | T50: 0 | U50: 0 | V50: 0 | W50: 0 | X50: 0 | Y50: 0 | Z50: 0 | AA50: 0 | AB50: 0 | AC50: 0 | AD50: 0 | AE50: 0 | AF50: 0 | AG50: 0 | AH50: 0 | AI50: 0 | AJ50: 0 | AK50: 0 | AM50: =SUM(O50:AL50) -> 0 | AN50: =IF(K50=0,"",(K50-N50-AL50)/K50) -> 0
A51: =IFERROR(VLOOKUP(C51,'Product List'!$A$2:$C198,2,FALSE),"") | B51: =IFERROR(VLOOKUP(C51,'Product List'!$A$2:$C198,3,FALSE),"") | E51: =+E50+1 -> 36 | F51: GUTTER | G51: 14500 | H51: 0 | I51: =+G51-H51 -> 14500 | J51: 0 | K51: =+I51+J51 -> 14500 | L51: =+K51/$K$190 -> 0.0010431655 | M51: =+K51/$T$9 -> 0.1763411 | N51: =+K51-SUM(O51:AL51) -> 14500 | O51: 0 | P51: 0 | Q51: 0 | R51: 0 | S51: 0 | T51: 0 | U51: 0 | V51: 0 | W51: 0 | X51: 0 | Y51: 0 | Z51: 0 | AA51: 0 | AB51: 0 | AC51: 0 | AD51: 0 | AE51: 0 | AF51: 0 | AG51: 0 | AH51: 0 | AI51: 0 | AJ51: 0 | AK51: 0 | AM51: =SUM(O51:AL51) -> 0 | AN51: =IF(K51=0,"",(K51-N51-AL51)/K51) -> 0
A52: =IFERROR(VLOOKUP(C52,'Product List'!$A$2:$C198,2,FALSE),"") | B52: =IFERROR(VLOOKUP(C52,'Product List'!$A$2:$C198,3,FALSE),"") | E52: 36 | F52: PLASTER FOUNDATION | G52: 4250 | H52: 0 | I52: =+G52-H52 -> 4250 | J52: 0 | K52: =+I52+J52 -> 4250 | L52: =+K52/$K$190 -> 0.0003057554 | M52: =+K52/$T$9 -> 0.051686186 | N52: =+K52-SUM(O52:AL52) -> 4250 | O52: 0 | P52: 0 | Q52: 0 | R52: 0 | S52: 0 | T52: 0 | U52: 0 | V52: 0 | W52: 0 | X52: 0 | Y52: 0 | Z52: 0 | AA52: 0 | AB52: 0 | AC52: 0 | AD52: 0 | AE52: 0 | AF52: 0 | AG52: 0 | AH52: 0 | AI52: 0 | AJ52: 0 | AK52: 0 | AM52: =SUM(O52:AL52) -> 0 | AN52: =IF(K52=0,"",(K52-N52-AL52)/K52) -> 0
A53: =IFERROR(VLOOKUP(C53,'Product List'!$A$2:$C198,2,FALSE),"") | B53: =IFERROR(VLOOKUP(C53,'Product List'!$A$2:$C198,3,FALSE),"") | E53: 37 | F53: ROOF HATCH | G53: 1600 | H53: 0 | I53: =+G53-H53 -> 1600 | J53: 0 | K53: =+I53+J53 -> 1600 | L53: =+K53/$K$190 -> 0.00011510791 | M53: =+K53/$T$9 -> 0.019458329 | N53: =+K53-SUM(O53:AL53) -> 1600 | O53: 0 | P53: 0 | Q53: 0 | R53: 0 | S53: 0 | T53: 0 | U53: 0 | V53: 0 | W53: 0 | X53: 0 | Y53: 0 | Z53: 0 | AA53: 0 | AB53: 0 | AC53: 0 | AD53: 0 | AE53: 0 | AF53: 0 | AG53: 0 | AH53: 0 | AI53: 0 | AJ53: 0 | AK53: 0 | AM53: =SUM(O53:AL53) -> 0 | AN53: =IF(K53=0,"",(K53-N53-AL53)/K53) -> 0
A54: =IFERROR(VLOOKUP(C54,'Product List'!$A$2:$C198,2,FALSE),"") | B54: =IFERROR(VLOOKUP(C54,'Product List'!$A$2:$C198,3,FALSE),"") | E54: 38 | F54: PICKLEBALL | G54: 35000 | H54: 0 | I54: =+G54-H54 -> 35000 | J54: 0 | K54: =+I54+J54 -> 35000 | L54: =+K54/$K$190 -> 0.0025179856 | M54: =+K54/$T$9 -> 0.42565094 | N54: =+K54-SUM(O54:AL54) -> 35000 | O54: 0 | P54: 0 | Q54: 0 | R54: 0 | S54: 0 | T54: 0 | U54: 0 | V54: 0 | W54: 0 | X54: 0 | Y54: 0 | Z54: 0 | AA54: 0 | AB54: 0 | AC54: 0 | AD54: 0 | AE54: 0 | AF54: 0 | AG54: 0 | AH54: 0 | AI54: 0 | AJ54: 0 | AK54: 0 | AM54: =SUM(O54:AL54) -> 0 | AN54: =IF(K54=0,"",(K54-N54-AL54)/K54) -> 0
A55: =IFERROR(VLOOKUP(C55,'Product List'!$A$2:$C198,2,FALSE),"") | B55: =IFERROR(VLOOKUP(C55,'Product List'!$A$2:$C198,3,FALSE),"") | E55: 39 | F55: 2 VAC STATIONS | G55: 7500 | H55: 0 | I55: =+G55-H55 -> 7500 | J55: 0 | K55: =+I55+J55 -> 7500 | L55: =+K55/$K$190 -> 0.00053956835 | M55: =+K55/$T$9 -> 0.091210916 | N55: =+K55-SUM(O55:AL55) -> 7500 | O55: 0 | P55: 0 | Q55: 0 | R55: 0 | S55: 0 | T55: 0 | U55: 0 | V55: 0 | W55: 0 | X55: 0 | Y55: 0 | Z55: 0 | AA55: 0 | AB55: 0 | AC55: 0 | AD55: 0 | AE55: 0 | AF55: 0 | AG55: 0 | AH55: 0 | AI55: 0 | AJ55: 0 | AK55: 0 | AM55: =SUM(O55:AL55) -> 0 | AN55: =IF(K55=0,"",(K55-N55-AL55)/K55) -> 0
A56: =IFERROR(VLOOKUP(C56,'Product List'!$A$2:$C198,2,FALSE),"") | B56: =IFERROR(VLOOKUP(C56,'Product List'!$A$2:$C198,3,FALSE),"") | E56: 40 | F56: MAILBOXES | G56: 16000 | H56: 0 | I56: =+G56-H56 -> 16000 | J56: 0 | K56: =+I56+J56 -> 16000 | L56: =+K56/$K$190 -> 0.0011510791 | M56: =+K56/$T$9 -> 0.19458329 | N56: =+K56-SUM(O56:AL56) -> 16000 | O56: 0 | P56: 0 | Q56: 0 | R56: 0 | S56: 0 | T56: 0 | U56: 0 | V56: 0 | W56: 0 | X56: 0 | Y56: 0 | Z56: 0 | AA56: 0 | AB56: 0 | AC56: 0 | AD56: 0 | AE56: 0 | AF56: 0 | AG56: 0 | AH56: 0 | AI56: 0 | AJ56: 0 | AK56: 0 | AM56: =SUM(O56:AL56) -> 0 | AN56: =IF(K56=0,"",(K56-N56-AL56)/K56) -> 0
A57: =IFERROR(VLOOKUP(C57,'Product List'!$A$2:$C198,2,FALSE),"") | B57: =IFERROR(VLOOKUP(C57,'Product List'!$A$2:$C198,3,FALSE),"") | E57: 41 | F57: DOG WASH STATION | G57: 5000 | H57: 0 | I57: =+G57-H57 -> 5000 | J57: 0 | K57: =+I57+J57 -> 5000 | L57: =+K57/$K$190 -> 0.00035971223 | M57: =+K57/$T$9 -> 0.060807277 | N57: =+K57-SUM(O57:AL57) -> 5000 | O57: 0 | P57: 0 | Q57: 0 | R57: 0 | S57: 0 | T57: 0 | U57: 0 | V57: 0 | W57: 0 | X57: 0 | Y57: 0 | Z57: 0 | AA57: 0 | AB57: 0 | AC57: 0 | AD57: 0 | AE57: 0 | AF57: 0 | AG57: 0 | AH57: 0 | AI57: 0 | AJ57: 0 | AK57: 0 | AM57: =SUM(O57:AL57) -> 0 | AN57: =IF(K57=0,"",(K57-N57-AL57)/K57) -> 0
A58: =IFERROR(VLOOKUP(C58,'Product List'!$A$2:$C198,2,FALSE),"") | B58: =IFERROR(VLOOKUP(C58,'Product List'!$A$2:$C198,3,FALSE),"") | E58: 42 | F58: BLINDS | G58: 25000 | H58: 0 | I58: =+G58-H58 -> 25000 | J58: 0 | K58: =+I58+J58 -> 25000 | L58: =+K58/$K$190 -> 0.0017985612 | M58: =+K58/$T$9 -> 0.30403639 | N58: =+K58-SUM(O58:AL58) -> 25000 | O58: 0 | P58: 0 | Q58: 0 | R58: 0 | S58: 0 | T58: 0 | U58: 0 | V58: 0 | W58: 0 | X58: 0 | Y58: 0 | Z58: 0 | AA58: 0 | AB58: 0 | AC58: 0 | AD58: 0 | AE58: 0 | AF58: 0 | AG58: 0 | AH58: 0 | AI58: 0 | AJ58: 0 | AK58: 0 | AM58: =SUM(O58:AL58) -> 0 | AN58: =IF(K58=0,"",(K58-N58-AL58)/K58) -> 0
A59: =IFERROR(VLOOKUP(C59,'Product List'!$A$2:$C198,2,FALSE),"") | B59: =IFERROR(VLOOKUP(C59,'Product List'!$A$2:$C198,3,FALSE),"") | E59: 43 | F59: 2 FIRE PITS | G59: 6000 | H59: 0 | I59: =+G59-H59 -> 6000 | J59: 0 | K59: =+I59+J59 -> 6000 | L59: =+K59/$K$190 -> 0.00043165468 | M59: =+K59/$T$9 -> 0.072968733 | N59: =+K59-SUM(O59:AL59) -> 6000 | O59: 0 | P59: 0 | Q59: 0 | R59: 0 | S59: 0 | T59: 0 | U59: 0 | V59: 0 | W59: 0 | X59: 0 | Y59: 0 | Z59: 0 | AA59: 0 | AB59: 0 | AC59: 0 | AD59: 0 | AE59: 0 | AF59: 0 | AG59: 0 | AH59: 0 | AI59: 0 | AJ59: 0 | AK59: 0 | AM59: =SUM(O59:AL59) -> 0 | AN59: =IF(K59=0,"",(K59-N59-AL59)/K59) -> 0
A60: =IFERROR(VLOOKUP(C60,'Product List'!$A$2:$C198,2,FALSE),"") | B60: =IFERROR(VLOOKUP(C60,'Product List'!$A$2:$C198,3,FALSE),"") | E60: 44 | F60: CLUB HOUSE PERGULA | G60: 30000 | H60: 0 | I60: =+G60-H60 -> 30000 | J60: 0 | K60: =+I60+J60 -> 30000 | L60: =+K60/$K$190 -> 0.0021582734 | M60: =+K60/$T$9 -> 0.36484366 | N60: =+K60-SUM(O60:AL60) -> 30000 | O60: 0 | P60: 0 | Q60: 0 | R60: 0 | S60: 0 | T60: 0 | U60: 0 | V60: 0 | W60: 0 | X60: 0 | Y60: 0 | Z60: 0 | AA60: 0 | AB60: 0 | AC60: 0 | AD60: 0 | AE60: 0 | AF60: 0 | AG60: 0 | AH60: 0 | AI60: 0 | AJ60: 0 | AK60: 0 | AM60: =SUM(O60:AL60) -> 0 | AN60: =IF(K60=0,"",(K60-N60-AL60)/K60) -> 0
A61: =IFERROR(VLOOKUP(C61,'Product List'!$A$2:$C198,2,FALSE),"") | B61: =IFERROR(VLOOKUP(C61,'Product List'!$A$2:$C198,3,FALSE),"") | E61: 45 | F61: KNOX BOX & FIRE LIDS | G61: 2450 | H61: 0 | I61: =+G61-H61 -> 2450 | J61: 0 | K61: =+I61+J61 -> 2450 | L61: =+K61/$K$190 -> 0.00017625899 | M61: =+K61/$T$9 -> 0.029795566 | N61: =+K61-SUM(O61:AL61) -> 2450 | O61: 0 | P61: 0 | Q61: 0 | R61: 0 | S61: 0 | T61: 0 | U61: 0 | V61: 0 | W61: 0 | X61: 0 | Y61: 0 | Z61: 0 | AA61: 0 | AB61: 0 | AC61: 0 | AD61: 0 | AE61: 0 | AF61: 0 | AG61: 0 | AH61: 0 | AI61: 0 | AJ61: 0 | AK61: 0 | AM61: =SUM(O61:AL61) -> 0 | AN61: =IF(K61=0,"",(K61-N61-AL61)/K61) -> 0
A62: =IFERROR(VLOOKUP(C62,'Product List'!$A$2:$C198,2,FALSE),"") | B62: =IFERROR(VLOOKUP(C62,'Product List'!$A$2:$C198,3,FALSE),"") | E62: 46 | F62: LANDSCAPE | G62: 125000 | H62: 0 | I62: =+G62-H62 -> 125000 | J62: 0 | K62: =+I62+J62 -> 125000 | L62: =+K62/$K$190 -> 0.0089928058 | M62: =+K62/$T$9 -> 1.5201819 | N62: =+K62-SUM(O62:AL62) -> 125000 | O62: 0 | P62: 0 | Q62: 0 | R62: 0 | S62: 0 | T62: 0 | U62: 0 | V62: 0 | W62: 0 | X62: 0 | Y62: 0 | Z62: 0 | AA62: 0 | AB62: 0 | AC62: 0 | AD62: 0 | AE62: 0 | AF62: 0 | AG62: 0 | AH62: 0 | AI62: 0 | AJ62: 0 | AK62: 0 | AM62: =SUM(O62:AL62) -> 0 | AN62: =IF(K62=0,"",(K62-N62-AL62)/K62) -> 0
A63: =IFERROR(VLOOKUP(C63,'Product List'!$A$2:$C198,2,FALSE),"") | B63: =IFERROR(VLOOKUP(C63,'Product List'!$A$2:$C198,3,FALSE),"") | E63: 47 | F63: APPLIANCES | G63: 264800 | H63: 0 | I63: =+G63-H63 -> 264800 | J63: 0 | K63: =+I63+J63 -> 264800 | L63: =+K63/$K$190 -> 0.01905036 | M63: =+K63/$T$9 -> 3.2203534 | N63: =+K63-SUM(O63:AL63) -> 264800 | O63: 0 | P63: 0 | Q63: 0 | R63: 0 | S63: 0 | T63: 0 | U63: 0 | V63: 0 | W63: 0 | X63: 0 | Y63: 0 | Z63: 0 | AA63: 0 | AB63: 0 | AC63: 0 | AD63: 0 | AE63: 0 | AF63: 0 | AG63: 0 | AH63: 0 | AI63: 0 | AJ63: 0 | AK63: 0 | AM63: =SUM(O63:AL63) -> 0 | AN63: =IF(K63=0,"",(K63-N63-AL63)/K63) -> 0
A64: =IFERROR(VLOOKUP(C64,'Product List'!$A$2:$C198,2,FALSE),"") | B64: =IFERROR(VLOOKUP(C64,'Product List'!$A$2:$C198,3,FALSE),"") | E64: 48 | F64: SIGNAGE | G64: 7500 | H64: 0 | I64: =+G64-H64 -> 7500 | J64: 0 | K64: =+I64+J64 -> 7500 | L64: =+K64/$K$190 -> 0.00053956835 | M64: =+K64/$T$9 -> 0.091210916 | N64: =+K64-SUM(O64:AL64) -> 7500 | O64: 0 | P64: 0 | Q64: 0 | R64: 0 | S64: 0 | T64: 0 | U64: 0 | V64: 0 | W64: 0 | X64: 0 | Y64: 0 | Z64: 0 | AA64: 0 | AB64: 0 | AC64: 0 | AD64: 0 | AE64: 0 | AF64: 0 | AG64: 0 | AH64: 0 | AI64: 0 | AJ64: 0 | AK64: 0 | AM64: =SUM(O64:AL64) -> 0 | AN64: =IF(K64=0,"",(K64-N64-AL64)/K64) -> 0
A65: =IFERROR(VLOOKUP(C65,'Product List'!$A$2:$C198,2,FALSE),"") | B65: =IFERROR(VLOOKUP(C65,'Product List'!$A$2:$C198,3,FALSE),"") | E65: 49 | F65: EXTERIOR FFE | G65: 10000 | H65: 0 | I65: =+G65-H65 -> 10000 | J65: 0 | K65: =+I65+J65 -> 10000 | L65: =+K65/$K$190 -> 0.00071942446 | M65: =+K65/$T$9 -> 0.12161455 | N65: =+K65-SUM(O65:AL65) -> 10000 | O65: 0 | P65: 0 | Q65: 0 | R65: 0 | S65: 0 | T65: 0 | U65: 0 | V65: 0 | W65: 0 | X65: 0 | Y65: 0 | Z65: 0 | AA65: 0 | AB65: 0 | AC65: 0 | AD65: 0 | AE65: 0 | AF65: 0 | AG65: 0 | AH65: 0 | AI65: 0 | AJ65: 0 | AK65: 0 | AM65: =SUM(O65:AL65) -> 0 | AN65: =IF(K65=0,"",(K65-N65-AL65)/K65) -> 0
A66: =IFERROR(VLOOKUP(C66,'Product List'!$A$2:$C198,2,FALSE),"") | B66: =IFERROR(VLOOKUP(C66,'Product List'!$A$2:$C198,3,FALSE),"") | E66: 50 | F66: CONTINGENCY | G66: 1243628.5 | H66: 0 | I66: =+G66-H66 -> 1243628.5 | J66: 0 | K66: =+I66+J66 -> 1243628.5 | L66: =+K66/$K$190 -> 0.089469678 | M66: =+K66/$T$9 -> 15.124333 | N66: =+K66-SUM(O66:AL66) -> 1243628.5 | O66: 0 | P66: 0 | Q66: 0 | R66: 0 | S66: 0 | T66: 0 | U66: 0 | V66: 0 | W66: 0 | X66: 0 | Y66: 0 | Z66: 0 | AA66: 0 | AB66: 0 | AC66: 0 | AD66: 0 | AE66: 0 | AF66: 0 | AG66: 0 | AH66: 0 | AI66: 0 | AJ66: 0 | AK66: 0 | AM66: =SUM(O66:AL66) -> 0 | AN66: =IF(K66=0,"",(K66-N66-AL66)/K66) -> 0
A67: =IFERROR(VLOOKUP(C67,'Product List'!$A$2:$C198,2,FALSE),"") | B67: =IFERROR(VLOOKUP(C67,'Product List'!$A$2:$C198,3,FALSE),"") | E67: 51 | F67: EQUIPMENT | G67: 25000 | H67: 0 | I67: =+G67-H67 -> 25000 | J67: 0 | K67: =+I67+J67 -> 25000 | L67: =+K67/$K$190 -> 0.0017985612 | M67: =+K67/$T$9 -> 0.30403639 | N67: =+K67-SUM(O67:AL67) -> 25000 | O67: 0 | P67: 0 | Q67: 0 | R67: 0 | S67: 0 | T67: 0 | U67: 0 | V67: 0 | W67: 0 | X67: 0 | Y67: 0 | Z67: 0 | AA67: 0 | AB67: 0 | AC67: 0 | AD67: 0 | AE67: 0 | AF67: 0 | AG67: 0 | AH67: 0 | AI67: 0 | AJ67: 0 | AK67: 0 | AM67: =SUM(O67:AL67) -> 0 | AN67: =IF(K67=0,"",(K67-N67-AL67)/K67) -> 0
A68: =IFERROR(VLOOKUP(C68,'Product List'!$A$2:$C198,2,FALSE),"") | B68: =IFERROR(VLOOKUP(C68,'Product List'!$A$2:$C198,3,FALSE),"") | E68: 53 | F68: HONEY BUCKET | G68: 7000 | H68: 565.69 | I68: =+G68-H68 -> 6434.31 | J68: 0 | K68: =+I68+J68 -> 6434.31 | L68: =+K68/$K$190 -> 0.0004629 | M68: =+K68/$T$9 -> 0.078250575 | N68: =+K68-SUM(O68:AL68) -> 4363.02 | O68: 373.54 | P68: 239.79 | Q68: 1457.96 | R68: 0 | S68: 0 | T68: 0 | U68: 0 | V68: 0 | W68: 0 | X68: 0 | Y68: 0 | Z68: 0 | AA68: 0 | AB68: 0 | AC68: 0 | AD68: 0 | AE68: 0 | AF68: 0 | AG68: 0 | AH68: 0 | AI68: 0 | AJ68: 0 | AK68: 0 | AM68: =SUM(O68:AL68) -> 2071.29 | AN68: =IF(K68=0,"",(K68-N68-AL68)/K68) -> 0.32191331
A69: =IFERROR(VLOOKUP(C69,'Product List'!$A$2:$C198,2,FALSE),"") | B69: =IFERROR(VLOOKUP(C69,'Product List'!$A$2:$C198,3,FALSE),"") | E69: 54 | F69: DUMPSTER | G69: 22000 | H69: 0 | I69: =+G69-H69 -> 22000 | J69: 0 | K69: =+I69+J69 -> 22000 | L69: =+K69/$K$190 -> 0.0015827338 | M69: =+K69/$T$9 -> 0.26755202 | N69: =+K69-SUM(O69:AL69) -> 19466.75 | O69: 75 | P69: 1042.4 | Q69: 1415.85 | R69: 0 | S69: 0 | T69: 0 | U69: 0 | V69: 0 | W69: 0 | X69: 0 | Y69: 0 | Z69: 0 | AA69: 0 | AB69: 0 | AC69: 0 | AD69: 0 | AE69: 0 | AF69: 0 | AG69: 0 | AH69: 0 | AI69: 0 | AJ69: 0 | AK69: 0 | AM69: =SUM(O69:AL69) -> 2533.25 | AN69: =IF(K69=0,"",(K69-N69-AL69)/K69) -> 0.11514773
A70: =IFERROR(VLOOKUP(C70,'Product List'!$A$2:$C198,2,FALSE),"") | B70: =IFERROR(VLOOKUP(C70,'Product List'!$A$2:$C198,3,FALSE),"") | E70: 55 | F70: TEMP FENCE | G70: 25000 | H70: 14030 | I70: =+G70-H70 -> 10970 | J70: 0 | K70: =+I70+J70 -> 10970 | L70: =+K70/$K$190 -> 0.00078920863 | M70: =+K70/$T$9 -> 0.13341117 | N70: =+K70-SUM(O70:AL70) -> 10970 | O70: 0 | P70: 0 | Q70: 0 | R70: 0 | S70: 0 | T70: 0 | U70: 0 | V70: 0 | W70: 0 | X70: 0 | Y70: 0 | Z70: 0 | AA70: 0 | AB70: 0 | AC70: 0 | AD70: 0 | AE70: 0 | AF70: 0 | AG70: 0 | AH70: 0 | AI70: 0 | AJ70: 0 | AK70: 0 | AM70: =SUM(O70:AL70) -> 0 | AN70: =IF(K70=0,"",(K70-N70-AL70)/K70) -> 0
A71: =IFERROR(VLOOKUP(C71,'Product List'!$A$2:$C198,2,FALSE),"") | B71: =IFERROR(VLOOKUP(C71,'Product List'!$A$2:$C198,3,FALSE),"") | E71: 56 | F71: CLEAN-UP LABOR | G71: 25000 | H71: 0 | I71: =+G71-H71 -> 25000 | J71: 0 | K71: =+I71+J71 -> 25000 | L71: =+K71/$K$190 -> 0.0017985612 | M71: =+K71/$T$9 -> 0.30403639 | N71: =+K71-SUM(O71:AL71) -> 25000 | O71: 0 | P71: 0 | Q71: 0 | R71: 0 | S71: 0 | T71: 0 | U71: 0 | V71: 0 | W71: 0 | X71: 0 | Y71: 0 | Z71: 0 | AA71: 0 | AB71: 0 | AC71: 0 | AD71: 0 | AE71: 0 | AF71: 0 | AG71: 0 | AH71: 0 | AI71: 0 | AJ71: 0 | AK71: 0 | AM71: =SUM(O71:AL71) -> 0 | AN71: =IF(K71=0,"",(K71-N71-AL71)/K71) -> 0
A72: =IFERROR(VLOOKUP(C72,'Product List'!$A$2:$C198,2,FALSE),"") | B72: =IFERROR(VLOOKUP(C72,'Product List'!$A$2:$C198,3,FALSE),"") | E72: 57 | F72: FINAL CLEAN | G72: 27000 | H72: 0 | I72: =+G72-H72 -> 27000 | J72: 0 | K72: =+I72+J72 -> 27000 | L72: =+K72/$K$190 -> 0.001942446 | M72: =+K72/$T$9 -> 0.3283593 | N72: =+K72-SUM(O72:AL72) -> 27000 | O72: 0 | P72: 0 | Q72: 0 | R72: 0 | S72: 0 | T72: 0 | U72: 0 | V72: 0 | W72: 0 | X72: 0 | Y72: 0 | Z72: 0 | AA72: 0 | AB72: 0 | AC72: 0 | AD72: 0 | AE72: 0 | AF72: 0 | AG72: 0 | AH72: 0 | AI72: 0 | AJ72: 0 | AK72: 0 | AM72: =SUM(O72:AL72) -> 0 | AN72: =IF(K72=0,"",(K72-N72-AL72)/K72) -> 0
A73: =IFERROR(VLOOKUP(C73,'Product List'!$A$2:$C198,2,FALSE),"") | B73: =IFERROR(VLOOKUP(C73,'Product List'!$A$2:$C198,3,FALSE),"") | E73: 58 | F73: STREET SWEEPING | G73: 4000 | H73: 0 | I73: =+G73-H73 -> 4000 | J73: 0 | K73: =+I73+J73 -> 4000 | L73: =+K73/$K$190 -> 0.00028776978 | M73: =+K73/$T$9 -> 0.048645822 | N73: =+K73-SUM(O73:AL73) -> 4000 | O73: 0 | P73: 0 | Q73: 0 | R73: 0 | S73: 0 | T73: 0 | U73: 0 | V73: 0 | W73: 0 | X73: 0 | Y73: 0 | Z73: 0 | AA73: 0 | AB73: 0 | AC73: 0 | AD73: 0 | AE73: 0 | AF73: 0 | AG73: 0 | AH73: 0 | AI73: 0 | AJ73: 0 | AK73: 0 | AM73: =SUM(O73:AL73) -> 0 | AN73: =IF(K73=0,"",(K73-N73-AL73)/K73) -> 0
A74: =IFERROR(VLOOKUP(C74,'Product List'!$A$2:$C198,2,FALSE),"") | B74: =IFERROR(VLOOKUP(C74,'Product List'!$A$2:$C198,3,FALSE),"") | E74: 59 | F74: CONC WASH OUT | G74: 4000 | H74: 0 | I74: =+G74-H74 -> 4000 | J74: 0 | K74: =+I74+J74 -> 4000 | L74: =+K74/$K$190 -> 0.00028776978 | M74: =+K74/$T$9 -> 0.048645822 | N74: =+K74-SUM(O74:AL74) -> 4000 | O74: 0 | P74: 0 | Q74: 0 | R74: 0 | S74: 0 | T74: 0 | U74: 0 | V74: 0 | W74: 0 | X74: 0 | Y74: 0 | Z74: 0 | AA74: 0 | AB74: 0 | AC74: 0 | AD74: 0 | AE74: 0 | AF74: 0 | AG74: 0 | AH74: 0 | AI74: 0 | AJ74: 0 | AK74: 0 | AM74: =SUM(O74:AL74) -> 0 | AN74: =IF(K74=0,"",(K74-N74-AL74)/K74) -> 0
A75: =IFERROR(VLOOKUP(C75,'Product List'!$A$2:$C198,2,FALSE),"") | B75: =IFERROR(VLOOKUP(C75,'Product List'!$A$2:$C198,3,FALSE),"") | E75: 60 | F75: SWPPP weekly inspection | G75: 9000 | H75: 0 | I75: =+G75-H75 -> 9000 | J75: 0 | K75: =+I75+J75 -> 9000 | L75: =+K75/$K$190 -> 0.00064748201 | M75: =+K75/$T$9 -> 0.1094531 | N75: =+K75-SUM(O75:AL75) -> 6750 | O75: 900 | P75: 450 | Q75: 900 | R75: 0 | S75: 0 | T75: 0 | U75: 0 | V75: 0 | W75: 0 | X75: 0 | Y75: 0 | Z75: 0 | AA75: 0 | AB75: 0 | AC75: 0 | AD75: 0 | AE75: 0 | AF75: 0 | AG75: 0 | AH75: 0 | AI75: 0 | AJ75: 0 | AK75: 0 | AM75: =SUM(O75:AL75) -> 2250 | AN75: =IF(K75=0,"",(K75-N75-AL75)/K75) -> 0.25
A76: =IFERROR(VLOOKUP(C76,'Product List'!$A$2:$C198,2,FALSE),"") | B76: =IFERROR(VLOOKUP(C76,'Product List'!$A$2:$C198,3,FALSE),"") | E76: 61 | F76: TEMP POWER | G76: 7500 | H76: 0 | I76: =+G76-H76 -> 7500 | J76: 0 | K76: =+I76+J76 -> 7500 | L76: =+K76/$K$190 -> 0.00053956835 | M76: =+K76/$T$9 -> 0.091210916 | N76: =+K76-SUM(O76:AL76) -> 5154.86 | O76: 243.49 | P76: 1797.51 | Q76: 304.14 | R76: 0 | S76: 0 | T76: 0 | U76: 0 | V76: 0 | W76: 0 | X76: 0 | Y76: 0 | Z76: 0 | AA76: 0 | AB76: 0 | AC76: 0 | AD76: 0 | AE76: 0 | AF76: 0 | AG76: 0 | AH76: 0 | AI76: 0 | AJ76: 0 | AK76: 0 | AM76: =SUM(O76:AL76) -> 2345.14 | AN76: =IF(K76=0,"",(K76-N76-AL76)/K76) -> 0.31268533
A77: =IFERROR(VLOOKUP(C77,'Product List'!$A$2:$C198,2,FALSE),"") | B77: =IFERROR(VLOOKUP(C77,'Product List'!$A$2:$C198,3,FALSE),"") | E77: 62 | F77: OFFICE TRAILER | G77: 13500 | H77: 0 | I77: =+G77-H77 -> 13500 | J77: 0 | K77: =+I77+J77 -> 13500 | L77: =+K77/$K$190 -> 0.00097122302 | M77: =+K77/$T$9 -> 0.16417965 | N77: =+K77-SUM(O77:AL77) -> 7874.77 | O77: 3299.17 | P77: 203.3 | Q77: 2122.76 | R77: 0 | S77: 0 | T77: 0 | U77: 0 | V77: 0 | W77: 0 | X77: 0 | Y77: 0 | Z77: 0 | AA77: 0 | AB77: 0 | AC77: 0 | AD77: 0 | AE77: 0 | AF77: 0 | AG77: 0 | AH77: 0 | AI77: 0 | AJ77: 0 | AK77: 0 | AM77: =SUM(O77:AL77) -> 5625.23 | AN77: =IF(K77=0,"",(K77-N77-AL77)/K77) -> 0.4166837
A78: =IFERROR(VLOOKUP(C78,'Product List'!$A$2:$C198,2,FALSE),"") | B78: =IFERROR(VLOOKUP(C78,'Product List'!$A$2:$C198,3,FALSE),"") | E78: 63 | F78: SECURITY CAMERAS | G78: 35000 | H78: 0 | I78: =+G78-H78 -> 35000 | J78: 0 | K78: =+I78+J78 -> 35000 | L78: =+K78/$K$190 -> 0.0025179856 | M78: =+K78/$T$9 -> 0.42565094 | N78: =+K78-SUM(O78:AL78) -> 26750 | O78: 2750 | P78: 2750 | Q78: 2750 | R78: 0 | S78: 0 | T78: 0 | U78: 0 | V78: 0 | W78: 0 | X78: 0 | Y78: 0 | Z78: 0 | AA78: 0 | AB78: 0 | AC78: 0 | AD78: 0 | AE78: 0 | AF78: 0 | AG78: 0 | AH78: 0 | AI78: 0 | AJ78: 0 | AK78: 0 | AM78: =SUM(O78:AL78) -> 8250 | AN78: =IF(K78=0,"",(K78-N78-AL78)/K78) -> 0.23571429
A79: =IFERROR(VLOOKUP(C79,'Product List'!$A$2:$C198,2,FALSE),"") | B79: =IFERROR(VLOOKUP(C79,'Product List'!$A$2:$C198,3,FALSE),"") | E79: 64 | F79: SPECIAL INSPECTIONS | G79: 10000 | H79: 4538 | I79: =+G79-H79 -> 5462 | J79: 0 | K79: =+I79+J79 -> 5462 | L79: =+K79/$K$190 -> 0.00039294964 | M79: =+K79/$T$9 -> 0.06642587 | N79: =+K79-SUM(O79:AL79) -> 1405.6 | O79: 74.8 | P79: 3720.8 | Q79: 260.8 | R79: 0 | S79: 0 | T79: 0 | U79: 0 | V79: 0 | W79: 0 | X79: 0 | Y79: 0 | Z79: 0 | AA79: 0 | AB79: 0 | AC79: 0 | AD79: 0 | AE79: 0 | AF79: 0 | AG79: 0 | AH79: 0 | AI79: 0 | AJ79: 0 | AK79: 0 | AM79: =SUM(O79:AL79) -> 4056.4 | AN79: =IF(K79=0,"",(K79-N79-AL79)/K79) -> 0.74265837
A80: =IFERROR(VLOOKUP(C80,'Product List'!$A$2:$C198,2,FALSE),"") | B80: =IFERROR(VLOOKUP(C80,'Product List'!$A$2:$C198,3,FALSE),"") | E80: 65 | F80: SAFTEY | G80: 7500 | H80: 0 | I80: =+G80-H80 -> 7500 | J80: 0 | K80: =+I80+J80 -> 7500 | L80: =+K80/$K$190 -> 0.00053956835 | M80: =+K80/$T$9 -> 0.091210916 | N80: =+K80-SUM(O80:AL80) -> 7500 | O80: 0 | P80: 0 | Q80: 0 | R80: 0 | S80: 0 | T80: 0 | U80: 0 | V80: 0 | W80: 0 | X80: 0 | Y80: 0 | Z80: 0 | AA80: 0 | AB80: 0 | AC80: 0 | AD80: 0 | AE80: 0 | AF80: 0 | AG80: 0 | AH80: 0 | AI80: 0 | AJ80: 0 | AK80: 0 | AM80: =SUM(O80:AL80) -> 0 | AN80: =IF(K80=0,"",(K80-N80-AL80)/K80) -> 0
A81: =IFERROR(VLOOKUP(C81,'Product List'!$A$2:$C198,2,FALSE),"") | B81: =IFERROR(VLOOKUP(C81,'Product List'!$A$2:$C198,3,FALSE),"") | E81: 66 | F81: GENERAL CONDITIONS | G81: 30000 | H81: 0 | I81: =+G81-H81 -> 30000 | J81: 0 | K81: =+I81+J81 -> 30000 | L81: =+K81/$K$190 -> 0.0021582734 | M81: =+K81/$T$9 -> 0.36484366 | N81: =+K81-SUM(O81:AL81) -> 30000 | O81: 0 | P81: 0 | Q81: 0 | R81: 0 | S81: 0 | T81: 0 | U81: 0 | V81: 0 | W81: 0 | X81: 0 | Y81: 0 | Z81: 0 | AA81: 0 | AB81: 0 | AC81: 0 | AD81: 0 | AE81: 0 | AF81: 0 | AG81: 0 | AH81: 0 | AI81: 0 | AJ81: 0 | AK81: 0 | AM81: =SUM(O81:AL81) -> 0 | AN81: =IF(K81=0,"",(K81-N81-AL81)/K81) -> 0
A82: =IFERROR(VLOOKUP(C82,'Product List'!$A$2:$C198,2,FALSE),"") | B82: =IFERROR(VLOOKUP(C82,'Product List'!$A$2:$C198,3,FALSE),"") | E82: 67 | F82: Insurance | G82: 180000 | H82: 171331 | I82: =+G82-H82 -> 8669 | J82: 0 | K82: =+I82+J82 -> 8669 | L82: =+K82/$K$190 -> 0.00062366906 | M82: =+K82/$T$9 -> 0.10542766 | N82: =+K82-SUM(O82:AL82) -> 8669 | O82: 0 | P82: 0 | Q82: 0 | R82: 0 | S82: 0 | T82: 0 | U82: 0 | V82: 0 | W82: 0 | X82: 0 | Y82: 0 | Z82: 0 | AA82: 0 | AB82: 0 | AC82: 0 | AD82: 0 | AE82: 0 | AF82: 0 | AG82: 0 | AH82: 0 | AI82: 0 | AJ82: 0 | AK82: 0 | AM82: =SUM(O82:AL82) -> 0 | AN82: =IF(K82=0,"",(K82-N82-AL82)/K82) -> 0
A83: =IFERROR(VLOOKUP(C83,'Product List'!$A$2:$C198,2,FALSE),"") | B83: =IFERROR(VLOOKUP(C83,'Product List'!$A$2:$C198,3,FALSE),"") | E83: 68 | F83: SITE SUPERVISION, PM, SUPER | G83: 260000 | H83: 27000 | I83: =+G83-H83 -> 233000 | J83: 0 | K83: =+I83+J83 -> 233000 | L83: =+K83/$K$190 -> 0.01676259 | M83: =+K83/$T$9 -> 2.8336191 | N83: =+K83-SUM(O83:AL83) -> 170000 | O83: 29000 | P83: 17000 | Q83: 17000 | R83: 0 | S83: 0 | T83: 0 | U83: 0 | V83: 0 | W83: 0 | X83: 0 | Y83: 0 | Z83: 0 | AA83: 0 | AB83: 0 | AC83: 0 | AD83: 0 | AE83: 0 | AF83: 0 | AG83: 0 | AH83: 0 | AI83: 0 | AJ83: 0 | AK83: 0 | AM83: =SUM(O83:AL83) -> 63000 | AN83: =IF(K83=0,"",(K83-N83-AL83)/K83) -> 0.27038627
A84: =IFERROR(VLOOKUP(C84,'Product List'!$A$2:$C198,2,FALSE),"") | B84: =IFERROR(VLOOKUP(C84,'Product List'!$A$2:$C198,3,FALSE),"") | E84: 69 | F84: Construction Profit | G84: 667000 | H84: 200000 | I84: =+G84-H84 -> 467000 | J84: 0 | K84: =+I84+J84 -> 467000 | L84: =+K84/$K$190 -> 0.033597122 | M84: =+K84/$T$9 -> 5.6793997 | N84: =+K84-SUM(O84:AL84) -> 467000 | O84: 0 | P84: 0 | Q84: 0 | R84: 0 | S84: 0 | T84: 0 | U84: 0 | V84: 0 | W84: 0 | X84: 0 | Y84: 0 | Z84: 0 | AA84: 0 | AB84: 0 | AC84: 0 | AD84: 0 | AE84: 0 | AF84: 0 | AG84: 0 | AH84: 0 | AI84: 0 | AJ84: 0 | AK84: 0 | AM84: =SUM(O84:AL84) -> 0 | AN84: =IF(K84=0,"",(K84-N84-AL84)/K84) -> 0
A85: =IFERROR(VLOOKUP(C85,'Product List'!$A$2:$C198,2,FALSE),"") | B85: =IFERROR(VLOOKUP(C85,'Product List'!$A$2:$C198,3,FALSE),"") | E85: 70 | F85: Soft Cost | G85: 588368.19 | H85: 588368.19 | I85: =+G85-H85 -> 0 | J85: 0 | K85: =+I85+J85 -> 0 | L85: =+K85/$K$190 -> 0 | M85: =+K85/$T$9 -> 0 | N85: =+K85-SUM(O85:AL85) -> 0 | O85: 0 | P85: 0 | Q85: 0 | R85: 0 | S85: 0 | T85: 0 | U85: 0 | V85: 0 | W85: 0 | X85: 0 | Y85: 0 | Z85: 0 | AA85: 0 | AB85: 0 | AC85: 0 | AD85: 0 | AE85: 0 | AF85: 0 | AG85: 0 | AH85: 0 | AI85: 0 | AJ85: 0 | AK85: 0 | AM85: =SUM(O85:AL85) -> 0 | AN85: =IF(K85=0,"",(K85-N85-AL85)/K85)
A86: =IFERROR(VLOOKUP(C86,'Product List'!$A$2:$C198,2,FALSE),"") | B86: =IFERROR(VLOOKUP(C86,'Product List'!$A$2:$C198,3,FALSE),"") | E86: 71 | F86: CM Fee | G86: 765501.37 | H86: 32517.84 | I86: =+G86-H86 -> 732983.53 | J86: 0 | K86: =+I86+J86 -> 732983.53 | L86: =+K86/$K$190 -> 0.052732628 | M86: =+K86/$T$9 -> 8.9141466 | N86: =+K86-SUM(O86:AL86) -> 599379.19 | O86: 31670.865 | P86: 45486.89 | Q86: 56446.59 | R86: 0 | S86: 0 | T86: 0 | U86: 0 | V86: 0 | W86: 0 | X86: 0 | Y86: 0 | Z86: 0 | AA86: 0 | AB86: 0 | AC86: 0 | AD86: 0 | AE86: 0 | AF86: 0 | AG86: 0 | AH86: 0 | AI86: 0 | AJ86: 0 | AK86: 0 | AM86: =SUM(O86:AL86) -> 133604.35 | AN86: =IF(K86=0,"",(K86-N86-AL86)/K86) -> 0.18227469
A87: =IFERROR(VLOOKUP(C87,'Product List'!$A$2:$C198,2,FALSE),"") | B87: =IFERROR(VLOOKUP(C87,'Product List'!$A$2:$C198,3,FALSE),"") | E87: 72 | G87: 0 | H87: 0 | I87: =+G87-H87 -> 0 | J87: 0 | K87: =+I87+J87 -> 0 | L87: =+K87/$K$190 -> 0 | M87: =+K87/$T$9 -> 0 | N87: =+K87-SUM(O87:AL87) -> 0 | O87: 0 | P87: 0 | Q87: 0 | R87: 0 | S87: 0 | T87: 0 | U87: 0 | V87: 0 | W87: 0 | X87: 0 | Y87: 0 | Z87: 0 | AA87: 0 | AB87: 0 | AC87: 0 | AD87: 0 | AE87: 0 | AF87: 0 | AG87: 0 | AH87: 0 | AI87: 0 | AJ87: 0 | AK87: 0 | AM87: =SUM(O87:AL87) -> 0 | AN87: =IF(K87=0,"",(K87-N87-AL87)/K87)
A88: =IFERROR(VLOOKUP(C88,'Product List'!$A$2:$C198,2,FALSE),"") | B88: =IFERROR(VLOOKUP(C88,'Product List'!$A$2:$C198,3,FALSE),"") | E88: 73 | G88: 0 | H88: 0 | I88: =+G88-H88 -> 0 | J88: 0 | K88: =+I88+J88 -> 0 | L88: =+K88/$K$190 -> 0 | M88: =+K88/$T$9 -> 0 | N88: =+K88-SUM(O88:AL88) -> 0 | O88: 0 | P88: 0 | Q88: 0 | R88: 0 | S88: 0 | T88: 0 | U88: 0 | V88: 0 | W88: 0 | X88: 0 | Y88: 0 | Z88: 0 | AA88: 0 | AB88: 0 | AC88: 0 | AD88: 0 | AE88: 0 | AF88: 0 | AG88: 0 | AH88: 0 | AI88: 0 | AJ88: 0 | AK88: 0 | AM88: =SUM(O88:AL88) -> 0 | AN88: =IF(K88=0,"",(K88-N88-AL88)/K88)
A89: =IFERROR(VLOOKUP(C89,'Product List'!$A$2:$C198,2,FALSE),"") | B89: =IFERROR(VLOOKUP(C89,'Product List'!$A$2:$C198,3,FALSE),"") | E89: 74 | G89: 0 | H89: 0 | I89: =+G89-H89 -> 0 | J89: 0 | K89: =+I89+J89 -> 0 | L89: =+K89/$K$190 -> 0 | M89: =+K89/$T$9 -> 0 | N89: =+K89-SUM(O89:AL89) -> 0 | O89: 0 | P89: 0 | Q89: 0 | R89: 0 | S89: 0 | T89: 0 | U89: 0 | V89: 0 | W89: 0 | X89: 0 | Y89: 0 | Z89: 0 | AA89: 0 | AB89: 0 | AC89: 0 | AD89: 0 | AE89: 0 | AF89: 0 | AG89: 0 | AH89: 0 | AI89: 0 | AJ89: 0 | AK89: 0 | AM89: =SUM(O89:AL89) -> 0 | AN89: =IF(K89=0,"",(K89-N89-AL89)/K89)
A90: =IFERROR(VLOOKUP(C90,'Product List'!$A$2:$C198,2,FALSE),"") | B90: =IFERROR(VLOOKUP(C90,'Product List'!$A$2:$C198,3,FALSE),"") | E90: 75 | G90: 0 | H90: 0 | I90: =+G90-H90 -> 0 | J90: 0 | K90: =+I90+J90 -> 0 | L90: =+K90/$K$190 -> 0 | M90: =+K90/$T$9 -> 0 | N90: =+K90-SUM(O90:AL90) -> 0 | O90: 0 | P90: 0 | Q90: 0 | R90: 0 | S90: 0 | T90: 0 | U90: 0 | V90: 0 | W90: 0 | X90: 0 | Y90: 0 | Z90: 0 | AA90: 0 | AB90: 0 | AC90: 0 | AD90: 0 | AE90: 0 | AF90: 0 | AG90: 0 | AH90: 0 | AI90: 0 | AJ90: 0 | AK90: 0 | AM90: =SUM(O90:AL90) -> 0 | AN90: =IF(K90=0,"",(K90-N90-AL90)/K90)
A91: =IFERROR(VLOOKUP(C91,'Product List'!$A$2:$C198,2,FALSE),"") | B91: =IFERROR(VLOOKUP(C91,'Product List'!$A$2:$C198,3,FALSE),"") | E91: 76 | G91: 0 | H91: 0 | I91: =+G91-H91 -> 0 | J91: 0 | K91: =+I91+J91 -> 0 | L91: =+K91/$K$190 -> 0 | M91: =+K91/$T$9 -> 0 | N91: =+K91-SUM(O91:AL91) -> 0 | O91: 0 | P91: 0 | Q91: 0 | R91: 0 | S91: 0 | T91: 0 | U91: 0 | V91: 0 | W91: 0 | X91: 0 | Y91: 0 | Z91: 0 | AA91: 0 | AB91: 0 | AC91: 0 | AD91: 0 | AE91: 0 | AF91: 0 | AG91: 0 | AH91: 0 | AI91: 0 | AJ91: 0 | AK91: 0 | AM91: =SUM(O91:AL91) -> 0 | AN91: =IF(K91=0,"",(K91-N91-AL91)/K91)
A92: =IFERROR(VLOOKUP(C92,'Product List'!$A$2:$C198,2,FALSE),"") | B92: =IFERROR(VLOOKUP(C92,'Product List'!$A$2:$C198,3,FALSE),"") | E92: 77 | G92: 0 | H92: 0 | I92: =+G92-H92 -> 0 | J92: 0 | K92: =+I92+J92 -> 0 | L92: =+K92/$K$190 -> 0 | M92: =+K92/$T$9 -> 0 | N92: =+K92-SUM(O92:AL92) -> 0 | O92: 0 | P92: 0 | Q92: 0 | R92: 0 | S92: 0 | T92: 0 | U92: 0 | V92: 0 | W92: 0 | X92: 0 | Y92: 0 | Z92: 0 | AA92: 0 | AB92: 0 | AC92: 0 | AD92: 0 | AE92: 0 | AF92: 0 | AG92: 0 | AH92: 0 | AI92: 0 | AJ92: 0 | AK92: 0 | AM92: =SUM(O92:AL92) -> 0 | AN92: =IF(K92=0,"",(K92-N92-AL92)/K92)
A93: =IFERROR(VLOOKUP(C93,'Product List'!$A$2:$C198,2,FALSE),"") | B93: =IFERROR(VLOOKUP(C93,'Product List'!$A$2:$C198,3,FALSE),"") | E93: 78 | G93: 0 | H93: 0 | I93: =+G93-H93 -> 0 | J93: 0 | K93: =+I93+J93 -> 0 | L93: =+K93/$K$190 -> 0 | M93: =+K93/$T$9 -> 0 | N93: =+K93-SUM(O93:AL93) -> 0 | O93: 0 | P93: 0 | Q93: 0 | R93: 0 | S93: 0 | T93: 0 | U93: 0 | V93: 0 | W93: 0 | X93: 0 | Y93: 0 | Z93: 0 | AA93: 0 | AB93: 0 | AC93: 0 | AD93: 0 | AE93: 0 | AF93: 0 | AG93: 0 | AH93: 0 | AI93: 0 | AJ93: 0 | AK93: 0 | AM93: =SUM(O93:AL93) -> 0 | AN93: =IF(K93=0,"",(K93-N93-AL93)/K93)
A94: =IFERROR(VLOOKUP(C94,'Product List'!$A$2:$C198,2,FALSE),"") | B94: =IFERROR(VLOOKUP(C94,'Product List'!$A$2:$C198,3,FALSE),"") | E94: 79 | G94: 0 | H94: 0 | I94: =+G94-H94 -> 0 | J94: 0 | K94: =+I94+J94 -> 0 | L94: =+K94/$K$190 -> 0 | M94: =+K94/$T$9 -> 0 | N94: =+K94-SUM(O94:AL94) -> 0 | O94: 0 | P94: 0 | Q94: 0 | R94: 0 | S94: 0 | T94: 0 | U94: 0 | V94: 0 | W94: 0 | X94: 0 | Y94: 0 | Z94: 0 | AA94: 0 | AB94: 0 | AC94: 0 | AD94: 0 | AE94: 0 | AF94: 0 | AG94: 0 | AH94: 0 | AI94: 0 | AJ94: 0 | AK94: 0 | AM94: =SUM(O94:AL94) -> 0 | AN94: =IF(K94=0,"",(K94-N94-AL94)/K94)
A95: =IFERROR(VLOOKUP(C95,'Product List'!$A$2:$C198,2,FALSE),"") | B95: =IFERROR(VLOOKUP(C95,'Product List'!$A$2:$C198,3,FALSE),"") | E95: 80 | G95: 0 | H95: 0 | I95: =+G95-H95 -> 0 | J95: 0 | K95: =+I95+J95 -> 0 | L95: =+K95/$K$190 -> 0 | M95: =+K95/$T$9 -> 0 | N95: =+K95-SUM(O95:AL95) -> 0 | O95: 0 | P95: 0 | Q95: 0 | R95: 0 | S95: 0 | T95: 0 | U95: 0 | V95: 0 | W95: 0 | X95: 0 | Y95: 0 | Z95: 0 | AA95: 0 | AB95: 0 | AC95: 0 | AD95: 0 | AE95: 0 | AF95: 0 | AG95: 0 | AH95: 0 | AI95: 0 | AJ95: 0 | AK95: 0 | AM95: =SUM(O95:AL95) -> 0 | AN95: =IF(K95=0,"",(K95-N95-AL95)/K95)
A96: =IFERROR(VLOOKUP(C96,'Product List'!$A$2:$C198,2,FALSE),"") | B96: =IFERROR(VLOOKUP(C96,'Product List'!$A$2:$C198,3,FALSE),"") | E96: 81 | G96: 0 | H96: 0 | I96: =+G96-H96 -> 0 | J96: 0 | K96: =+I96+J96 -> 0 | L96: =+K96/$K$190 -> 0 | M96: =+K96/$T$9 -> 0 | N96: =+K96-SUM(O96:AL96) -> 0 | O96: 0 | P96: 0 | Q96: 0 | R96: 0 | S96: 0 | T96: 0 | U96: 0 | V96: 0 | W96: 0 | X96: 0 | Y96: 0 | Z96: 0 | AA96: 0 | AB96: 0 | AC96: 0 | AD96: 0 | AE96: 0 | AF96: 0 | AG96: 0 | AH96: 0 | AI96: 0 | AJ96: 0 | AK96: 0 | AM96: =SUM(O96:AL96) -> 0 | AN96: =IF(K96=0,"",(K96-N96-AL96)/K96)
A97: =IFERROR(VLOOKUP(C97,'Product List'!$A$2:$C198,2,FALSE),"") | B97: =IFERROR(VLOOKUP(C97,'Product List'!$A$2:$C198,3,FALSE),"") | E97: 82 | G97: 0 | H97: 0 | I97: =+G97-H97 -> 0 | J97: 0 | K97: =+I97+J97 -> 0 | L97: =+K97/$K$190 -> 0 | M97: =+K97/$T$9 -> 0 | N97: =+K97-SUM(O97:AL97) -> 0 | O97: 0 | P97: 0 | Q97: 0 | R97: 0 | S97: 0 | T97: 0 | U97: 0 | V97: 0 | W97: 0 | X97: 0 | Y97: 0 | Z97: 0 | AA97: 0 | AB97: 0 | AC97: 0 | AD97: 0 | AE97: 0 | AF97: 0 | AG97: 0 | AH97: 0 | AI97: 0 | AJ97: 0 | AK97: 0 | AM97: =SUM(O97:AL97) -> 0 | AN97: =IF(K97=0,"",(K97-N97-AL97)/K97)
A98: =IFERROR(VLOOKUP(C98,'Product List'!$A$2:$C198,2,FALSE),"") | B98: =IFERROR(VLOOKUP(C98,'Product List'!$A$2:$C198,3,FALSE),"") | E98: 83 | G98: 0 | H98: 0 | I98: =+G98-H98 -> 0 | J98: 0 | K98: =+I98+J98 -> 0 | L98: =+K98/$K$190 -> 0 | M98: =+K98/$T$9 -> 0 | N98: =+K98-SUM(O98:AL98) -> 0 | O98: 0 | P98: 0 | Q98: 0 | R98: 0 | S98: 0 | T98: 0 | U98: 0 | V98: 0 | W98: 0 | X98: 0 | Y98: 0 | Z98: 0 | AA98: 0 | AB98: 0 | AC98: 0 | AD98: 0 | AE98: 0 | AF98: 0 | AG98: 0 | AH98: 0 | AI98: 0 | AJ98: 0 | AK98: 0 | AM98: =SUM(O98:AL98) -> 0 | AN98: =IF(K98=0,"",(K98-N98-AL98)/K98)
A99: =IFERROR(VLOOKUP(C99,'Product List'!$A$2:$C198,2,FALSE),"") | B99: =IFERROR(VLOOKUP(C99,'Product List'!$A$2:$C198,3,FALSE),"") | E99: 84 | G99: 0 | H99: 0 | I99: =+G99-H99 -> 0 | J99: 0 | K99: =+I99+J99 -> 0 | L99: =+K99/$K$190 -> 0 | M99: =+K99/$T$9 -> 0 | N99: =+K99-SUM(O99:AL99) -> 0 | O99: 0 | P99: 0 | Q99: 0 | R99: 0 | S99: 0 | T99: 0 | U99: 0 | V99: 0 | W99: 0 | X99: 0 | Y99: 0 | Z99: 0 | AA99: 0 | AB99: 0 | AC99: 0 | AD99: 0 | AE99: 0 | AF99: 0 | AG99: 0 | AH99: 0 | AI99: 0 | AJ99: 0 | AK99: 0 | AM99: =SUM(O99:AL99) -> 0 | AN99: =IF(K99=0,"",(K99-N99-AL99)/K99)
A100: =IFERROR(VLOOKUP(C100,'Product List'!$A$2:$C198,2,FALSE),"") | B100: =IFERROR(VLOOKUP(C100,'Product List'!$A$2:$C198,3,FALSE),"") | E100: 85 | G100: 0 | H100: 0 | I100: =+G100-H100 -> 0 | J100: 0 | K100: =+I100+J100 -> 0 | L100: =+K100/$K$190 -> 0 | M100: =+K100/$T$9 -> 0 | N100: =+K100-SUM(O100:AL100) -> 0 | O100: 0 | P100: 0 | Q100: 0 | R100: 0 | S100: 0 | T100: 0 | U100: 0 | V100: 0 | W100: 0 | X100: 0 | Y100: 0 | Z100: 0 | AA100: 0 | AB100: 0 | AC100: 0 | AD100: 0 | AE100: 0 | AF100: 0 | AG100: 0 | AH100: 0 | AI100: 0 | AJ100: 0 | AK100: 0 | AM100: =SUM(O100:AL100) -> 0 | AN100: =IF(K100=0,"",(K100-N100-AL100)/K100)
...
