Workbook

Sheet Cost To Complete
C2: Hunter's Landing Continuation Sheet
I5: Rich Development
F6: Scheduled Value
B7: Item # | C7: # | D7: DESCRIPTION OF WORK | F7: Rich Development | G7: Change Orders/Reallocation | H7: Total | I7: Amount Paid to Date | J7: Retention held to Date | K7: Contract cost to complete including retention | L7: Change Order cost to complete including retention | M7: TOTAL COST TO COMPLETE | N7: DIFFERENCE BETWEEN SCHEDULED VALUE AND COST TO COMPLETE
P8: NOTES
B10: 001 | C10: EXCAVATION/SITE | D10: Survey | F10: 5500 | G10: 515 | H10: =F10+G10 -> 6015 | I10: 6015 | J10: 0 | K10: 750 | M10: =J10+K10+L10 -> 750 | N10: =H10-I10-M10 -> -750 | P10: Fencing & Pond surveys
B11: 002 | C11: EXCAVATION/SITE | D11: Excavation | F11: 364814.62 | H11: =F11+G11 -> 364814.62 | I11: =SUM('Continuation Sheet'!I11:O11) -> 284961.84 | J11: 26859.91 | K11: =29346+57493 -> 86839 | L11: =10535+5000 -> 15535 | M11: =J11+K11+L11 -> 129233.91 | N11: =H11-I11-M11 -> -49381.13
B12: 003 | C12: EXCAVATION/SITE | D12: Concrete | F12: 208293.28 | H12: =F12+G12 -> 208293.28 | I12: =SUM('Continuation Sheet'!I12:O12) -> 127580.19 | J12: =3614.11 -> 3614.11 | K12: =38640.58+31928.33+15000 -> 85568.91 | M12: =J12+K12+L12 -> 89183.02 | N12: =H12-I12-M12 -> -8469.93
B13: 004 | C13: EXCAVATION/SITE | D13: 12th UDOT | F13: 17550 | H13: =F13+G13 -> 17550 | I13: =SUM('Continuation Sheet'!I13:O13) -> 0 | K13: 49414 | L13: =66495+3000 -> 69495 | M13: =J13+K13+L13 -> 118909 | N13: =H13-I13-M13 -> -101359
B14: 005 | C14: EXCAVATION/SITE | D14: All Fencing | F14: 44475 | H14: =F14+G14 -> 44475 | I14: =SUM('Continuation Sheet'!I14:O14) -> 0 | K14: 44475 | L14: =3845+3714.31 -> 7559.31 | M14: =J14+K14+L14 -> 52034.31 | N14: =H14-I14-M14 -> -7559.31
B15: 006 | C15: EXCAVATION/SITE | D15: Track out Pad entire building | F15: 49700 | H15: =F15+G15 -> 49700 | I15: =SUM('Continuation Sheet'!I15:O15) -> 49700 | M15: =J15+K15+L15 -> 0 | N15: =H15-I15-M15 -> 0
B16: 007 | C16: FRAME/ROOF | D16: Turnkey Frame/Garage | F16: 43755 | G16: -20000 | H16: =F16+G16 -> 23755 | I16: =SUM('Continuation Sheet'!I16:O16) -> 16365.04 | J16: 851.75 | M16: =J16+K16+L16 -> 851.75 | N16: =H16-I16-M16 -> 6538.21
B17: 008 | C17: FRAME/ROOF | D17: Garage Roof | F17: 12500 | H17: =F17+G17 -> 12500 | I17: =SUM('Continuation Sheet'!I17:O17) -> 0 | K17: 12500 | M17: =J17+K17+L17 -> 12500 | N17: =H17-I17-M17 -> 0
B18: 009 | C18: FRAME/ROOF | D18: Roofing L&M | F18: 63244 | H18: =F18+G18 -> 63244 | I18: =SUM('Continuation Sheet'!I18:O18) -> 50372.23 | J18: =4242.8 -> 4242.8 | K18: =27500+3244.18 -> 30744.18 | M18: =J18+K18+L18 -> 34986.98 | N18: =H18-I18-M18 -> -22115.21
B19: 010 | C19: FRAME/ROOF | D19: Deck Coatings | F19: 97940 | H19: =F19+G19 -> 97940 | I19: =SUM('Continuation Sheet'!I19:O19) -> 80613.2 | J19: =1066.92+4242.8 -> 5309.72 | K19: =5761 -> 5761 | L19: 10598.4 | M19: =J19+K19+L19 -> 21669.12 | N19: =H19-I19-M19 -> -4342.32 | P19: Decks lvl 2-5 done, Urbane needs to bill the rest of their contract amount, My Roof has a bill for the rest of the amentities deck change order
B20: 011 | C20: FRAME/ROOF | D20: Structural Steel-Parking | F20: 84577 | G20: -24000 | H20: =F20+G20 -> 60577 | I20: =SUM('Continuation Sheet'!I20:O20) -> 0 | J20: 17699.18 | M20: =J20+K20+L20 -> 17699.18 | N20: =H20-I20-M20 -> 42877.82
B21: 012 | C21: FRAME/ROOF | D21: All other Steel Features | F21: 623901.14 | G21: -221107.65 | H21: =F21+G21 -> 402793.49 | I21: =SUM('Continuation Sheet'!I21:O21) -> 250237.61 | M21: =J21+K21+L21 -> 0 | N21: =H21-I21-M21 -> 152555.88
B22: 013 | C22: FRAME/ROOF | D22: Garage Door For Trash | F22: 4500 | H22: =F22+G22 -> 4500 | I22: =SUM('Continuation Sheet'!I22:O22) -> 0 | M22: =J22+K22+L22 -> 0 | N22: =H22-I22-M22 -> 4500
B23: 014 | C23: FRAME/ROOF | D23: Store Front Labor | F23: 7500 | G23: 5053.48 | H23: =F23+G23 -> 12553.48 | I23: =SUM('Continuation Sheet'!I23:O23) -> 12553.48 | M23: =J23+K23+L23 -> 0 | N23: =H23-I23-M23 -> 0
B24: 015 | C24: FRAME/ROOF | D24: Elevator | F24: 70150 | H24: =F24+G24 -> 70150 | I24: =SUM('Continuation Sheet'!I24:O24) -> 0 | M24: =J24+K24+L24 -> 0 | N24: =H24-I24-M24 -> 70150
B25: 016 | C25: FRAME/ROOF | D25: HM Door Labor | F25: 52475 | G25: -19908.96 | H25: =F25+G25 -> 32566.04 | I25: =SUM('Continuation Sheet'!I25:O25) -> 32480.8 | M25: =J25+K25+L25 -> 0 | N25: =H25-I25-M25 -> 85.24
B26: 017 | C26: MEP TRADES | D26: Plumbing | F26: 524500 | H26: =F26+G26 -> 524500 | I26: =SUM('Continuation Sheet'!I26:O26) -> 381460.72 | J26: =2200 -> 2200 | K26: =3600+3600+60080 -> 67280 | M26: =J26+K26+L26 -> 69480 | N26: =H26-I26-M26 -> 73559.28
B27: 018 | C27: MEP TRADES | D27: HVAC | F27: 1244900 | H27: =F27+G27 -> 1244900 | I27: =SUM('Continuation Sheet'!I27:O27) -> 934132.15 | M27: =J27+K27+L27 -> 0 | N27: =H27-I27-M27 -> 310767.85
B28: 019 | C28: MEP TRADES | D28: Electric | F28: 434737.1 | H28: =F28+G28 -> 434737.1 | I28: =SUM('Continuation Sheet'!I28:O28) -> 129850.11 | M28: =J28+K28+L28 -> 0 | N28: =H28-I28-M28 -> 304886.99
B29: 020 | C29: MEP TRADES | D29: 3 Electric Car Station | F29: 37500 | H29: =F29+G29 -> 37500 | I29: =SUM('Continuation Sheet'!I29:O29) -> 0 | M29: =J29+K29+L29 -> 0 | N29: =H29-I29-M29 -> 37500
B30: 021 | C30: MEP TRADES | D30: Sprinkler System | F30: 168681 | H30: =F30+G30 -> 168681 | I30: =SUM('Continuation Sheet'!I30:O30) -> 91342.53 | M30: =J30+K30+L30 -> 0 | N30: =H30-I30-M30 -> 77338.47
B31: 022 | C31: MEP TRADES | D31: Fire Caulk | F31: 14750 | H31: =F31+G31 -> 14750 | I31: =SUM('Continuation Sheet'!I31:O31) -> 3515.03 | M31: =J31+K31+L31 -> 0 | N31: =H31-I31-M31 -> 11234.97
B32: 023 | C32: FINISHES | D32: Gypcrete | F32: 152486 | H32: =F32+G32 -> 152486 | I32: =SUM('Continuation Sheet'!I32:O32) -> 141181.97 | M32: =J32+K32+L32 -> 0 | N32: =H32-I32-M32 -> 11304.03
B33: 024 | C33: FINISHES | D33: Insulation | F33: 222919 | G33: -25000 | H33: =F33+G33 -> 197919 | I33: =SUM('Continuation Sheet'!I33:O33) -> 184045.4 | J33: 9686.6 | M33: =J33+K33+L33 -> 9686.6 | N33: =H33-I33-M33 -> 4187
B34: 025 | C34: FINISHES | D34: Sheetrock | F34: 1467345 | H34: =F34+G34 -> 1467345 | I34: =SUM('Continuation Sheet'!I34:O34) -> 1126879.1 | J34: =51371.44+3875 -> 55246.44 | K34: =357781.56 -> 357781.56 | M34: =J34+K34+L34 -> 413028 | N34: =H34-I34-M34 -> -72562.14 | P34: Cabinets/Countertops were taken out of this category because there was no category funded for them
B35: 026 | C35: FINISHES | D35: Finish Materials Misc | F35: 25000 | G35: 146985.68 | H35: =F35+G35 -> 171985.68 | I35: =SUM('Continuation Sheet'!I35:O35) -> 170079.85 | M35: =J35+K35+L35 -> 0 | N35: =H35-I35-M35 -> 1905.83
B36: 027 | C36: FINISHES | D36: Finish Labor | F36: 189135 | G36: -50313.72 | H36: =F36+G36 -> 138821.28 | I36: =SUM('Continuation Sheet'!I36:O36) -> 135233.66 | M36: =J36+K36+L36 -> 0 | N36: =H36-I36-M36 -> 3587.62
B37: 028 | C37: FINISHES | D37: Interior Paint | F37: 303668.8 | H37: =F37+G37 -> 303668.8 | I37: =SUM('Continuation Sheet'!I37:O37) -> 136304.72 | M37: =J37+K37+L37 -> 0 | N37: =H37-I37-M37 -> 167364.08
B38: 029 | C38: FINISHES | D38: Equipment Cabinets | F38: 6000 | H38: =F38+G38 -> 6000 | I38: =SUM('Continuation Sheet'!I38:O38) -> 0 | M38: =J38+K38+L38 -> 0 | N38: =H38-I38-M38 -> 6000
B39: 030 | C39: FINISHES | D39: Garage Doors | F39: 14081.4 | H39: =F39+G39 -> 14081.4 | I39: =SUM('Continuation Sheet'!I39:O39) -> 0 | M39: =J39+K39+L39 -> 0 | N39: =H39-I39-M39 -> 14081.4
B40: 031 | C40: FINISHES | D40: Floor Prep | F40: 10000 | H40: =F40+G40 -> 10000 | I40: =SUM('Continuation Sheet'!I40:O40) -> 0 | M40: =J40+K40+L40 -> 0 | N40: =H40-I40-M40 -> 10000
B41: 032 | C41: FINISHES | D41: Hardware & Install Labor | F41: 65000 | H41: =F41+G41 -> 65000 | I41: =SUM('Continuation Sheet'!I41:O41) -> 15682.52 | M41: =J41+K41+L41 -> 0 | N41: =H41-I41-M41 -> 49317.48
B42: 033 | C42: FINISHES | D42: Fire Extinguishers | F42: 7850 | H42: =F42+G42 -> 7850 | I42: =SUM('Continuation Sheet'!I42:O42) -> 0 | M42: =J42+K42+L42 -> 0 | N42: =H42-I42-M42 -> 7850
B43: 034 | C43: FINISHES | D43: Mirrors | F43: 24750 | G43: -15000 | H43: =F43+G43 -> 9750 | I43: =SUM('Continuation Sheet'!I43:O43) -> 0 | M43: =J43+K43+L43 -> 0 | N43: =H43-I43-M43 -> 9750
B44: 035 | C44: FINISHES | D44: Flooring,Wall Tile M&L | F44: 340975 | H44: =F44+G44 -> 340975 | I44: =SUM('Continuation Sheet'!I44:O44) -> 172071.22 | M44: =J44+K44+L44 -> 0 | N44: =H44-I44-M44 -> 168903.78
B45: 036 | C45: EXTERIORS & MISC | D45: Brick | F45: 342000 | G45: 9500 | H45: =F45+G45 -> 351500 | I45: =SUM('Continuation Sheet'!I45:O45) -> 351500 | M45: =J45+K45+L45 -> 0 | N45: =H45-I45-M45 -> 0
B46: 037 | C46: EXTERIORS & MISC | D46: Stucco EFIS,Soffit,Fascia | F46: 437274.1 | H46: =F46+G46 -> 437274.1 | I46: =SUM('Continuation Sheet'!I46:O46) -> 383782.04 | J46: =15459.94+904.05+3271.01+553.3 -> 20188.3 | K46: =154361.29+18081+11066+12130.32 -> 195638.61 | M46: =J46+K46+L46 -> 215826.91 | N46: =H46-I46-M46 -> -162334.85
B47: 038 | C47: EXTERIORS & MISC | D47: Gutter | F47: 10245 | H47: =F47+G47 -> 10245 | I47: =SUM('Continuation Sheet'!I47:O47) -> 0 | M47: =J47+K47+L47 -> 0 | N47: =H47-I47-M47 -> 10245
B48: 039 | C48: EXTERIORS & MISC | D48: Plaster Foundation | F48: 4250 | H48: =F48+G48 -> 4250 | I48: =SUM('Continuation Sheet'!I48:O48) -> 0 | M48: =J48+K48+L48 -> 0 | N48: =H48-I48-M48 -> 4250
B49: 040 | C49: EXTERIORS & MISC | D49: Roof Hatch | F49: 1600 | H49: =F49+G49 -> 1600 | I49: =SUM('Continuation Sheet'!I49:O49) -> 0 | M49: =J49+K49+L49 -> 0 | N49: =H49-I49-M49 -> 1600
B50: 041 | C50: EXTERIORS & MISC | D50: Trash Chute | F50: 37850 | H50: =F50+G50 -> 37850 | I50: =SUM('Continuation Sheet'!I50:O50) -> 0 | M50: =J50+K50+L50 -> 0 | N50: =H50-I50-M50 -> 37850
B51: 042 | C51: EXTERIORS & MISC | D51: Pool | F51: 257092 | H51: =F51+G51 -> 257092 | I51: =SUM('Continuation Sheet'!I51:O51) -> 0 | K51: 257092 | M51: =J51+K51+L51 -> 257092 | N51: =H51-I51-M51 -> 0
B52: 043 | C52: EXTERIORS & MISC | D52: Knox box & Fire Lids | F52: 2450 | H52: =F52+G52 -> 2450 | I52: =SUM('Continuation Sheet'!I52:O52) -> 0 | K52: 2450 | M52: =J52+K52+L52 -> 2450 | N52: =H52-I52-M52 -> 0
B53: 044 | C53: ALLOWANCES | D53: Landscape | F53: 184000 | G53: -15000 | H53: =F53+G53 -> 169000 | I53: =SUM('Continuation Sheet'!I53:O53) -> 0 | K53: 169000 | M53: =J53+K53+L53 -> 169000 | N53: =H53-I53-M53 -> 0
B54: 045 | C54: ALLOWANCES | D54: Appliances | F54: 517942.26 | H54: =F54+G54 -> 517942.26 | I54: =SUM('Continuation Sheet'!I54:O54) -> 520418.99 | M54: =J54+K54+L54 -> 0 | N54: =H54-I54-M54 -> -2476.73
B55: 046 | C55: ALLOWANCES | D55: Signage | F55: 15000 | H55: =F55+G55 -> 15000 | I55: =SUM('Continuation Sheet'!I55:O55) -> 0 | K55: =15000 -> 15000 | L55: 20000 | M55: =J55+K55+L55 -> 35000 | N55: =H55-I55-M55 -> -20000 | P55: Owner provided sign? CO?
B56: 047 | C56: ALLOWANCES | D56: All Amenities | F56: 25000 | H56: =F56+G56 -> 25000 | I56: =SUM('Continuation Sheet'!I56:O56) -> 7222.64 | M56: =J56+K56+L56 -> 0 | N56: =H56-I56-M56 -> 17777.36
B57: 048 | C57: ALLOWANCES | D57: Garden Shed & Pad | F57: 8000 | H57: =F57+G57 -> 8000 | I57: =SUM('Continuation Sheet'!I57:O57) -> 0 | K57: 8000 | M57: =J57+K57+L57 -> 8000 | N57: =H57-I57-M57 -> 0 | P57: Allowance & Owner provided. Need to find exact cost
B58: 049 | C58: ALLOWANCES | D58: Blinds | F58: 42500 | H58: =F58+G58 -> 42500 | I58: =SUM('Continuation Sheet'!I58:O58) -> 26645.75 | J58: 1402.41 | K58: 17943.84 | M58: =J58+K58+L58 -> 19346.25 | N58: =H58-I58-M58 -> -3492
B59: 050 | C59: GENERAL | D59: Contingency | F59: 250000 | G59: -43882.07 | H59: =F59+G59 -> 206117.93 | I59: =SUM('Continuation Sheet'!I59:O59) -> 166495.25 | M59: =J59+K59+L59 -> 0 | N59: =H59-I59-M59 -> 39622.68
B60: 051 | C60: GENERAL | D60: Equipment | F60: 25000 | H60: =F60+G60 -> 25000 | I60: =SUM('Continuation Sheet'!I60:O60) -> 25000 | M60: =J60+K60+L60 -> 0 | N60: =H60-I60-M60 -> 0
B61: 052 | C61: GENERAL | D61: Honey Bucket | F61: 7000 | H61: =F61+G61 -> 7000 | I61: =SUM('Continuation Sheet'!I61:O61) -> 6856.9 | K61: 3500 | M61: =J61+K61+L61 -> 3500 | N61: =H61-I61-M61 -> -3356.9
B62: 053 | C62: GENERAL | D62: Dumpster | F62: 25000 | G62: 815.83 | H62: =F62+G62 -> 25815.83 | I62: =SUM('Continuation Sheet'!I62:O62) -> 25815.83 | K62: 20000 | M62: =J62+K62+L62 -> 20000 | N62: =H62-I62-M62 -> -20000
B63: 054 | C63: GENERAL | D63: Temp Fence | F63: 6000 | H63: =F63+G63 -> 6000 | I63: =SUM('Continuation Sheet'!I63:O63) -> 0 | M63: =J63+K63+L63 -> 0 | N63: =H63-I63-M63 -> 6000
B64: 055 | C64: GENERAL | D64: Clean-up Labor | F64: 30000 | H64: =F64+G64 -> 30000 | I64: =SUM('Continuation Sheet'!I64:O64) -> 14395 | K64: 15605 | M64: =J64+K64+L64 -> 15605 | N64: =H64-I64-M64 -> 0
B65: 056 | C65: GENERAL | D65: Final Clean | F65: 50000 | H65: =F65+G65 -> 50000 | I65: =SUM('Continuation Sheet'!I65:O65) -> 0 | K65: 50000 | M65: =J65+K65+L65 -> 50000 | N65: =H65-I65-M65 -> 0
B66: 057 | C66: GENERAL | D66: Street Sweeping | F66: 5000 | H66: =F66+G66 -> 5000 | I66: =SUM('Continuation Sheet'!I66:O66) -> 0 | K66: 5000 | M66: =J66+K66+L66 -> 5000 | N66: =H66-I66-M66 -> 0
B67: 058 | C67: GENERAL | D67: Conc Wash Out | F67: 5000 | H67: =F67+G67 -> 5000 | I67: =SUM('Continuation Sheet'!I67:O67) -> 0 | M67: =J67+K67+L67 -> 0 | N67: =H67-I67-M67 -> 5000
B68: 059 | C68: GENERAL | D68: SWPPP/split w/cu inspections | F68: 3500 | G68: 140 | H68: =F68+G68 -> 3640 | I68: =SUM('Continuation Sheet'!I68:O68) -> 3640 | K68: 3000 | M68: =J68+K68+L68 -> 3000 | N68: =H68-I68-M68 -> -3000
B69: 060 | C69: GENERAL | D69: Temp Power | F69: 7500 | H69: =F69+G69 -> 7500 | I69: =SUM('Continuation Sheet'!I69:O69) -> 4958.13 | K69: 2541.87 | M69: =J69+K69+L69 -> 2541.87 | N69: =H69-I69-M69 -> 0
B70: 061 | C70: GENERAL | D70: Office Trailer | F70: 15000 | H70: =F70+G70 -> 15000 | I70: =SUM('Continuation Sheet'!I70:O70) -> 6462.81 | K70: 8537.19 | M70: =J70+K70+L70 -> 8537.19 | N70: =H70-I70-M70 -> 0
B71: 062 | C71: GENERAL | D71: Security Cameras | F71: 30000 | H71: =F71+G71 -> 30000 | I71: =SUM('Continuation Sheet'!I71:O71) -> 12423.09 | K71: 10000 | M71: =J71+K71+L71 -> 10000 | N71: =H71-I71-M71 -> 7576.91 | P71: Do we need a change order for the building security system?
B72: 063 | C72: GENERAL | D72: Special Inspections | F72: 15000 | H72: =F72+G72 -> 15000 | I72: =SUM('Continuation Sheet'!I72:O72) -> 14393.68 | K72: 606.32 | M72: =J72+K72+L72 -> 606.32 | N72: =H72-I72-M72 -> 0
B73: 064 | C73: GENERAL | D73: Saftey | F73: 10000 | G73: -5000 | H73: =F73+G73 -> 5000 | I73: =SUM('Continuation Sheet'!I73:O73) -> 0 | M73: =J73+K73+L73 -> 0 | N73: =H73-I73-M73 -> 5000
B74: 065 | C74: GENERAL | D74: General Conditions | F74: 30000 | H74: =F74+G74 -> 30000 | I74: =SUM('Continuation Sheet'!I74:O74) -> 3914.39 | K74: 26085.61 | M74: =J74+K74+L74 -> 26085.61 | N74: =H74-I74-M74 -> 0
B75: 066 | C75: GENERAL | D75: Insurance Not Builders | F75: 25000 | H75: =F75+G75 -> 25000 | I75: =SUM('Continuation Sheet'!I75:O75) -> 19.98 | M75: =J75+K75+L75 -> 0 | N75: =H75-I75-M75 -> 24980.02
B76: 067 | C76: GENERAL | D76: Site Supervision | F76: 240000 | H76: =F76+G76 -> 240000 | I76: =SUM('Continuation Sheet'!I76:O76) -> 183225 | K76: =17500*5 -> 87500 | M76: =J76+K76+L76 -> 87500 | N76: =H76-I76-M76 -> -30725
B77: 068 | C77: GENERAL | D77: Construction Profit | F77: 6583.94 | H77: =F77+G77 -> 6583.94 | I77: =SUM('Continuation Sheet'!I77:O77) -> 0 | K77: 606582 | M77: =J77+K77+L77 -> 606582 | N77: =H77-I77-M77 -> -599998.06
B78: 069 | C78: GENERAL | D78: Exterior Wall Project | F78: 483915.5 | G78: 276202.41 | H78: =F78+G78 -> 760117.91 | I78: =SUM('Continuation Sheet'!I78:O78) -> 760117.91 | M78: =J78+K78+L78 -> 0 | N78: =H78-I78-M78 -> -1.1641532e-10
D80: TOTALS | F80: =SUM(F10:F79) -> 10159856 | G80: =SUM(G10:G79) -> 0 | H80: =SUM(H10:H79) -> 10159856 | I80: =SUM(I10:I78) -> 7049945.8 | J80: =SUM(J10:J78) -> 147301.22 | K80: =SUM(K10:K78) -> 2245196.1 | L80: =SUM(L10:L78) -> 123187.71 | M80: =SUM(M10:M78) -> 2515685 | N80: =SUM(N10:N78) -> 594225.32

Sheet Continuation Sheet
C2: Hunter's Landing Continuation Sheet
I5: Rich Development
F6: Scheduled Value | I6: 45533 | J6: 45546 | T6: Retainage | V6: COST TO COMPLETE
B7: Item # | C7: # | D7: DESCRIPTION OF WORK | F7: Rich Development | G7: Change Orders/Reallocation | H7: Total | I7: Draw 20 | J7: Draw 21 | K7: Draw 22 | L7: Draw 23 | M7: Draw 24 | N7: Draw 25 | O7: Draw 26 | P7: Draw 27 | Q7: TOTAL COMPLETED AND STORED TO DATE | R7: Percent Complete | S7: BALANCE TO FINISH | T7: Value 5% | V7: Contract Amount | W7: Retention | X7: CO Amount for cost to complete | Y7: Project CO | Z7: CO #
B10: 001 | C10: EXCAVATION/SITE | D10: Survey | F10: 5500 | G10: 515 | H10: =F10+G10 -> 6015 | K10: 1340 | M10: 4675 | Q10: =SUM(I10:P10) -> 6015 | R10: =Q10/H10 -> 1 | S10: =H10-Q10 -> 0 | V10: 750 | X10: 0
B11: 002 | C11: EXCAVATION/SITE | D11: Excavation | F11: 364814.62 | H11: =F11+G11 -> 364814.62 | J11: 11270 | M11: 273691.84 | P11: =59368.35+37886.95 -> 97255.3 | Q11: =SUM(I11:P11) -> 382217.14 | R11: =Q11/H11 -> 1.0477024 | S11: =H11-Q11 -> -17402.52 | V11: 97255.3 | W11: 38228.61
B12: 003 | C12: EXCAVATION/SITE | D12: Concrete | F12: 208293.28 | H12: =F12+G12 -> 208293.28 | K12: =192.62+710.13+795+20433.48+29710.3 -> 51841.53 | L12: =8299.2+8187.9 -> 16487.1 | M12: =14946.08+483.38+913.5+1539.25+2352.28+2921.58+1325.59+2176.28+1354.54+2128.01+687.56+2351.28+2176.28 -> 35355.61 | O12: =7008.42+1175+15712.53 -> 23895.95 | P12: =15064.46+18288.05+16863.87 -> 50216.38 | Q12: =SUM(I12:P12) -> 177796.57 | R12: =Q12/H12 -> 0.85358764 | S12: =H12-Q12 -> 30496.71 | V12: =P12+S12 -> 80713.09 | W12: =3988.61 -> 3988.61
B13: 004 | C13: EXCAVATION/SITE | D13: 12th UDOT | F13: 17550 | H13: =F13+G13 -> 17550 | Q13: =SUM(I13:P13) -> 0 | R13: =Q13/H13 -> 0 | S13: =H13-Q13 -> 17550 | V13: =S13 -> 17550 | X13: =66495+25000 -> 91495
B14: 005 | C14: EXCAVATION/SITE | D14: All Fencing | F14: 44475 | H14: =F14+G14 -> 44475 | P14: 10035.61 | Q14: =SUM(I14:P14) -> 10035.61 | R14: =Q14/H14 -> 0.22564609 | S14: =H14-Q14 -> 34439.39 | V14: =S14 -> 34439.39 | W14: 119 | X14: =2616+1230+3714.31 -> 7560.31
B15: 006 | C15: EXCAVATION/SITE | D15: Track out Pad entire building | F15: 49700 | H15: =F15+G15 -> 49700 | I15: 37020 | J15: 12680 | Q15: =SUM(I15:P15) -> 49700 | R15: =Q15/H15 -> 1 | S15: =H15-Q15 -> 0 | V15: 0 | Y15: 61154.15
B16: 007 | C16: FRAME/ROOF | D16: Turnkey Frame/Garage | F16: 43755 | G16: -20000 | H16: =F16+G16 -> 23755 | K16: =181.79+16183.25 -> 16365.04 | Q16: =SUM(I16:P16) -> 16365.04 | R16: =Q16/H16 -> 0.68890928 | S16: =H16-Q16 -> 7389.96 | V16: 0 | W16: =851.75 -> 851.75
B17: 008 | C17: FRAME/ROOF | D17: Garage Roof | F17: 12500 | H17: =F17+G17 -> 12500 | Q17: =SUM(I17:P17) -> 0 | R17: =Q17/H17 -> 0 | S17: =H17-Q17 -> 12500
B18: 009 | C18: FRAME/ROOF | D18: Roofing L&M | F18: 63244 | H18: =F18+G18 -> 63244 | L18: 30100.75 | O18: 20271.48 | P18: 41081.98 | Q18: =SUM(I18:P18) -> 91454.21 | R18: =Q18/H18 -> 1.4460535 | S18: =H18-Q18 -> -28210.21
B19: 010 | C19: FRAME/ROOF | D19: Deck Coatings | F19: 97940 | H19: =F19+G19 -> 97940 | M19: 80613.2 | P19: 10068.48 | Q19: =SUM(I19:P19) -> 90681.68 | R19: =Q19/H19 -> 0.92589014 | S19: =H19-Q19 -> 7258.32 | X19: 32000 | AA19: Amenities Deck
B20: 011 | C20: FRAME/ROOF | D20: Structural Steel-Parking | F20: 84577 | G20: -24000 | H20: =F20+G20 -> 60577 | P20: =1706.9+3372.5 -> 5079.4 | Q20: =SUM(I20:P20) -> 5079.4 | R20: =Q20/H20 -> 0.083850306 | S20: =H20-Q20 -> 55497.6 | V20: =S20 -> 55497.6 | W20: 17699.18 | X20: 3550
B21: 012 | C21: FRAME/ROOF | D21: All other Steel Features | F21: 623901.14 | G21: -221107.65 | H21: =F21+G21 -> 402793.49 | I21: 15311.37 | J21: 4548.58 | K21: =352.1+310.68+2916.45+523.7+1048.15+786.03+89.44+7191.56 -> 13218.11 | M21: 217159.55 | P21: =115752.27 -> 115752.27 | Q21: =SUM(I21:P21) -> 365989.88 | R21: =Q21/H21 -> 0.90862908 | S21: =H21-Q21 -> 36803.61 | V21: =S21 -> 36803.61
B22: 013 | C22: FRAME/ROOF | D22: Garage Door For Trash | F22: 4500 | H22: =F22+G22 -> 4500 | Q22: =SUM(I22:P22) -> 0 | R22: =Q22/H22 -> 0 | S22: =H22-Q22 -> 4500 | V22: =S22 -> 4500
B23: 014 | C23: FRAME/ROOF | D23: Store Front Labor | F23: 7500 | G23: 5053.48 | H23: =F23+G23 -> 12553.48 | J23: 7500 | K23: 5053.48 | Q23: =SUM(I23:P23) -> 12553.48 | R23: =Q23/H23 -> 1 | S23: =H23-Q23 -> 0 | V23: 0
B24: 015 | C24: FRAME/ROOF | D24: Elevator | F24: 70150 | H24: =F24+G24 -> 70150 | P24: 18316.72 | Q24: =SUM(I24:P24) -> 18316.72 | R24: =Q24/H24 -> 0.26110791 | S24: =H24-Q24 -> 51833.28 | V24: =S24 -> 51833.28
B25: 016 | C25: FRAME/ROOF | D25: HM Door Labor | F25: 52475 | G25: -19908.96 | H25: =F25+G25 -> 32566.04 | K25: 1500 | N25: 20015.96 | O25: 10964.84 | P25: 39584.35 | Q25: =SUM(I25:P25) -> 72065.15 | R25: =Q25/H25 -> 2.2128926 | S25: =H25-Q25 -> -39499.11 | X25: 17364.5
B26: 017 | C26: MEP TRADES | D26: Plumbing | F26: 524500 | H26: =F26+G26 -> 524500 | I26: 60000 | K26: 124504.85 | L26: 45610.81 | M26: 72610.06 | N26: 38780 | O26: 39955 | P26: 60080 | Q26: =SUM(I26:P26) -> 441540.72 | R26: =Q26/H26 -> 0.84183169 | S26: =H26-Q26 -> 82959.28 | V26: =S26 -> 82959.28 | AA26: Needs to match
B27: 018 | C27: MEP TRADES | D27: HVAC | F27: 1244900 | H27: =F27+G27 -> 1244900 | K27: 204250 | L27: 199500 | M27: 309673.4 | N27: 135208.75 | O27: 85500 | P27: =162938.3 -> 162938.3 | Q27: =SUM(I27:P27) -> 1097070.4 | R27: =Q27/H27 -> 0.88125187 | S27: =H27-Q27 -> 147829.55 | V27: =S27 -> 147829.55
B28: 019 | C28: MEP TRADES | D28: Electric | F28: 434737.1 | H28: =F28+G28 -> 434737.1 | J28: 77050.11 | L28: 51300 | M28: 1500 | P28: 118750 | Q28: =SUM(I28:P28) -> 248600.11 | R28: =Q28/H28 -> 0.57184011 | S28: =H28-Q28 -> 186136.99 | V28: =S28 -> 186136.99
B29: 020 | C29: MEP TRADES | D29: 3 Electric Car Station | F29: 37500 | H29: =F29+G29 -> 37500 | Q29: =SUM(I29:P29) -> 0 | R29: =Q29/H29 -> 0 | S29: =H29-Q29 -> 37500 | V29: =S29 -> 37500
B30: 021 | C30: MEP TRADES | D30: Sprinkler System | F30: 168681 | H30: =F30+G30 -> 168681 | J30: 30210.79 | K30: 44259.74 | L30: 15466 | N30: 1406 | P30: 1406 | Q30: =SUM(I30:P30) -> 92748.53 | R30: =Q30/H30 -> 0.54984574 | S30: =H30-Q30 -> 75932.47 | V30: =S30 -> 75932.47
B31: 022 | C31: MEP TRADES | D31: Fire Caulk | F31: 14750 | H31: =F31+G31 -> 14750 | M31: 423.37 | O31: 3091.66 | P31: =4500+4500 -> 9000 | Q31: =SUM(I31:P31) -> 12515.03 | R31: =Q31/H31 -> 0.84847661 | S31: =H31-Q31 -> 2234.97 | V31: =S31 -> 2234.97
B32: 023 | C32: FINISHES | D32: Gypcrete | F32: 152486 | H32: =F32+G32 -> 152486 | J32: 92390.22 | L32: 15200 | M32: 20900 | N32: 12458.92 | O32: 232.83 | P32: 3135 | Q32: =SUM(I32:P32) -> 144316.97 | R32: =Q32/H32 -> 0.94642767 | S32: =H32-Q32 -> 8169.03 | V32: =S32 -> 8169.03
B33: 024 | C33: FINISHES | D33: Insulation | F33: 222919 | G33: -25000 | H33: =F33+G33 -> 197919 | L33: 117346.28 | M33: 1433.31 | N33: 52303.94 | O33: 12961.87 | Q33: =SUM(I33:P33) -> 184045.4 | R33: =Q33/H33 -> 0.92990264 | S33: =H33-Q33 -> 13873.6 | V33: =S33 -> 13873.6
B34: 025 | C34: FINISHES | D34: Sheetrock | F34: 1467345 | H34: =F34+G34 -> 1467345 | K34: =554084.18-27704.21 -> 526379.97 | L34: 233987.48 | M34: 131595 | O34: =157720+10688.77+66507.92 -> 234916.69 | P34: =5447.61+131594.99 -> 137042.6 | Q34: =SUM(I34:P34) -> 1263921.7 | R34: =Q34/H34 -> 0.86136644 | S34: =H34-Q34 -> 203423.26 | V34: =S34 -> 203423.26
B35: 026 | C35: FINISHES | D35: Finish Materials Misc | F35: 25000 | G35: 146985.68 | H35: =F35+G35 -> 171985.68 | K35: =4867.76+160.24+480.7+9662.93+168 -> 15339.63 | L35: =1081.08+4321.85 -> 5402.93 | M35: =7568.08+75+9977.31+75+75+11568.85+1554.74+2302.59+165.16+75+19908.96+1225.47 -> 54571.16 | N35: =19383.87+102.78+227.03 -> 19713.68 | O35: =986.49+5821.55+3746.54+2650.74+1118.32+739.87+253.55+3746.54+1423.74+3355.33+732.66+4028.15+468.32+5968.05+3044.07+777.47+1082.08+93.25+4750.42+1555.45+1397.53+4009.26+4367.36+3980.7+2547.33+1094.69+4497+6815.99 -> 75052.45 | P35: =27357.55+1968.69+24.56 -> 29350.8 | Q35: =SUM(I35:P35) -> 199430.65 | R35: =Q35/H35 -> 1.1595771 | S35: =H35-Q35 -> -27444.97 | X35: 30000 | Y35: Door rebuild
B36: 027 | C36: FINISHES | D36: Finish Labor | F36: 189135 | G36: -50313.72 | H36: =F36+G36 -> 138821.28 | K36: =13552 -> 13552 | L36: =6024.25+11275.97+48652.42 -> 65952.64 | M36: =685.2+16113.15 -> 16798.35 | O36: =38930.67 -> 38930.67 | P36: =23257.27 -> 23257.27 | Q36: =SUM(I36:P36) -> 158490.93 | R36: =Q36/H36 -> 1.1416905 | S36: =H36-Q36 -> -19669.65 | V36: =S36 -> -19669.65 | X36: 31000 | Y36: Door rebuild
B37: 028 | C37: FINISHES | D37: Interior Paint | F37: 303668.8 | H37: =F37+G37 -> 303668.8 | L37: 16999.73 | N37: 28686.67 | O37: 90618.32 | P37: 169506.27 | Q37: =SUM(I37:P37) -> 305810.99 | R37: =Q37/H37 -> 1.0070544 | S37: =H37-Q37 -> -2142.19 | V37: =S37 -> -2142.19
B38: 029 | C38: FINISHES | D38: Equipment Cabinets | F38: 6000 | H38: =F38+G38 -> 6000 | Q38: =SUM(I38:P38) -> 0 | R38: =Q38/H38 -> 0 | S38: =H38-Q38 -> 6000 | V38: =S38 -> 6000
B39: 030 | C39: FINISHES | D39: Garage Doors | F39: 14081.4 | H39: =F39+G39 -> 14081.4 | P39: =5089.74+10728.37 -> 15818.11 | Q39: =SUM(I39:P39) -> 15818.11 | R39: =Q39/H39 -> 1.1233336 | S39: =H39-Q39 -> -1736.71 | V39: =S39 -> -1736.71 | X39: 3000
B40: 031 | C40: FINISHES | D40: Floor Prep | F40: 10000 | H40: =F40+G40 -> 10000 | P40: 3673.39 | Q40: =SUM(I40:P40) -> 3673.39 | R40: =Q40/H40 -> 0.367339 | S40: =H40-Q40 -> 6326.61 | V40: =S40 -> 6326.61
B41: 032 | C41: FINISHES | D41: Hardware & Install Labor | F41: 65000 | H41: =F41+G41 -> 65000 | N41: 6806.48 | O41: =847.44+245+7783.6 -> 8876.04 | P41: 859.58 | Q41: =SUM(I41:P41) -> 16542.1 | R41: =Q41/H41 -> 0.25449385 | S41: =H41-Q41 -> 48457.9 | V41: =S41 -> 48457.9 | X41: 19065.45 | Y41: Door rebuild
B42: 033 | C42: FINISHES | D42: Fire Extinguishers | F42: 7850 | H42: =F42+G42 -> 7850 | P42: 4811.75 | Q42: =SUM(I42:P42) -> 4811.75 | R42: =Q42/H42 -> 0.61296178 | S42: =H42-Q42 -> 3038.25 | V42: =S42 -> 3038.25
B43: 034 | C43: FINISHES | D43: Mirrors | F43: 24750 | G43: -15000 | H43: =F43+G43 -> 9750 | P43: 6051.5 | Q43: =SUM(I43:P43) -> 6051.5 | R43: =Q43/H43 -> 0.62066667 | S43: =H43-Q43 -> 3698.5 | V43: =S43 -> 3698.5
B44: 035 | C44: FINISHES | D44: Flooring,Wall Tile M&L | F44: 340975 | H44: =F44+G44 -> 340975 | L44: 99384 | M44: 13764.08 | N44: 17929.49 | O44: 40993.65 | P44: =86933.77 -> 86933.77 | Q44: =SUM(I44:P44) -> 259004.99 | R44: =Q44/H44 -> 0.75960111 | S44: =H44-Q44 -> 81970.01 | V44: =S44 -> 81970.01
B45: 036 | C45: EXTERIORS & MISC | D45: Brick | F45: 342000 | G45: 9500 | H45: =F45+G45 -> 351500 | K45: 95000 | L45: 95000 | M45: 66500 | O45: 95000 | P45: =76000+5429.33 -> 81429.33 | Q45: =SUM(I45:P45) -> 432929.33 | R45: =Q45/H45 -> 1.2316624 | S45: =H45-Q45 -> -81429.33 | X45: 98500 | Y45: Difference between budget & contract amount
B46: 037 | C46: EXTERIORS & MISC | D46: Stucco EFIS,Soffit,Fascia | F46: 437274.1 | H46: =F46+G46 -> 437274.1 | K46: =204.53+65420.1-3271.01 -> 62353.62 | N46: 135571.74 | O46: 185856.68 | P46: =185856.68 -> 185856.68 | Q46: =SUM(I46:P46) -> 569638.72 | R46: =Q46/H46 -> 1.302704 | S46: =H46-Q46 -> -132364.62 | V46: =S46 -> -132364.62
B47: 038 | C47: EXTERIORS & MISC | D47: Gutter | F47: 10245 | H47: =F47+G47 -> 10245 | Q47: =SUM(I47:P47) -> 0 | R47: =Q47/H47 -> 0 | S47: =H47-Q47 -> 10245 | V47: =S47 -> 10245
B48: 039 | C48: EXTERIORS & MISC | D48: Plaster Foundation | F48: 4250 | H48: =F48+G48 -> 4250 | Q48: =SUM(I48:P48) -> 0 | R48: =Q48/H48 -> 0 | S48: =H48-Q48 -> 4250 | V48: =S48 -> 4250
B49: 040 | C49: EXTERIORS & MISC | D49: Roof Hatch | F49: 1600 | H49: =F49+G49 -> 1600 | Q49: =SUM(I49:P49) -> 0 | R49: =Q49/H49 -> 0 | S49: =H49-Q49 -> 1600 | V49: =S49 -> 1600
B50: 041 | C50: EXTERIORS & MISC | D50: Trash Chute | F50: 37850 | H50: =F50+G50 -> 37850 | Q50: =SUM(I50:P50) -> 0 | R50: =Q50/H50 -> 0 | S50: =H50-Q50 -> 37850 | V50: =S50 -> 37850
B51: 042 | C51: EXTERIORS & MISC | D51: Pool | F51: 257092 | H51: =F51+G51 -> 257092 | P51: =138008.97 -> 138008.97 | Q51: =SUM(I51:P51) -> 138008.97 | R51: =Q51/H51 -> 0.53680772 | S51: =H51-Q51 -> 119083.03 | V51: =S51 -> 119083.03
B52: 043 | C52: EXTERIORS & MISC | D52: Knox box & Fire Lids | F52: 2450 | H52: =F52+G52 -> 2450 | P52: 1272.3 | Q52: =SUM(I52:P52) -> 1272.3 | R52: =Q52/H52 -> 0.51930612 | S52: =H52-Q52 -> 1177.7 | V52: =S52 -> 1177.7
B53: 044 | C53: ALLOWANCES | D53: Landscape | F53: 184000 | G53: -15000 | H53: =F53+G53 -> 169000 | P53: =78001.63 -> 78001.63 | Q53: =SUM(I53:P53) -> 78001.63 | R53: =Q53/H53 -> 0.46154811 | S53: =H53-Q53 -> 90998.37 | V53: =S53 -> 90998.37
B54: 045 | C54: ALLOWANCES | D54: Appliances | F54: 517942.26 | H54: =F54+G54 -> 517942.26 | O54: =97540.46+422878.53 -> 520418.99 | Q54: =SUM(I54:P54) -> 520418.99 | R54: =Q54/H54 -> 1.0047819 | S54: =H54-Q54 -> -2476.73 | V54: =S54 -> -2476.73 | X54: 3000
B55: 046 | C55: ALLOWANCES | D55: Signage | F55: 15000 | H55: =F55+G55 -> 15000 | P55: 4956 | Q55: =SUM(I55:P55) -> 4956 | R55: =Q55/H55 -> 0.3304 | S55: =H55-Q55 -> 10044 | V55: =S55 -> 10044
B56: 047 | C56: ALLOWANCES | D56: All Amenities | F56: 25000 | H56: =F56+G56 -> 25000 | O56: 7222.64 | Q56: =SUM(I56:P56) -> 7222.64 | R56: =Q56/H56 -> 0.2889056 | S56: =H56-Q56 -> 17777.36 | V56: =S56 -> 17777.36
B57: 048 | C57: ALLOWANCES | D57: Garden Shed & Pad | F57: 8000 | H57: =F57+G57 -> 8000 | Q57: =SUM(I57:P57) -> 0 | R57: =Q57/H57 -> 0 | S57: =H57-Q57 -> 8000 | V57: =S57 -> 8000
B58: 049 | C58: ALLOWANCES | D58: Blinds | F58: 42500 | H58: =F58+G58 -> 42500 | N58: 26645.75 | P58: =17046.65 -> 17046.65 | Q58: =SUM(I58:P58) -> 43692.4 | R58: =Q58/H58 -> 1.0280565 | S58: =H58-Q58 -> -1192.4 | V58: =S58 -> -1192.4
B59: 050 | C59: GENERAL | D59: Contingency | F59: 250000 | G59: -43882.07 | H59: =F59+G59 -> 206117.93 | I59: 72500 | J59: 55251.03 | N59: 2663.35 | O59: =8274.01+26865.31+941.55 -> 36080.87 | P59: 175 | Q59: =SUM(I59:P59) -> 166670.25 | R59: =Q59/H59 -> 0.80861597 | S59: =H59-Q59 -> 39447.68
B60: 051 | C60: GENERAL | D60: Equipment | F60: 25000 | H60: =F60+G60 -> 25000 | I60: 10000 | J60: 15000 | Q60: =SUM(I60:P60) -> 25000 | R60: =Q60/H60 -> 1 | S60: =H60-Q60 -> 0 | V60: 0
B61: 052 | C61: GENERAL | D61: Honey Bucket | F61: 7000 | H61: =F61+G61 -> 7000 | J61: 362.35 | K61: =699.4+699.4+699.4 -> 2098.2 | M61: =699.4+739.39+739.39 -> 2178.18 | N61: =739.39 -> 739.39 | O61: 1478.78 | P61: 1478.78 | Q61: =SUM(I61:P61) -> 8335.68 | R61: =Q61/H61 -> 1.1908114 | S61: =H61-Q61 -> -1335.68 | V61: =S61 -> -1335.68 | X61: 1500
B62: 053 | C62: GENERAL | D62: Dumpster | F62: 25000 | G62: 815.83 | H62: =F62+G62 -> 25815.83 | K62: =251.63+260.43+271.43+914.66+7253.28 -> 8951.43 | L62: 4698.26 | M62: 3953.04 | N62: =4758.94 -> 4758.94 | O62: 3454.16 | P62: =11466.75+6095.62 -> 17562.37 | Q62: =SUM(I62:P62) -> 43378.2 | R62: =Q62/H62 -> 1.6802946 | S62: =H62-Q62 -> -17562.37 | X62: 2500
B63: 054 | C63: GENERAL | D63: Temp Fence | F63: 6000 | H63: =F63+G63 -> 6000 | Q63: =SUM(I63:P63) -> 0 | R63: =Q63/H63 -> 0 | S63: =H63-Q63 -> 6000 | V63: =S63 -> 6000
B64: 055 | C64: GENERAL | D64: Clean-up Labor | F64: 30000 | H64: =F64+G64 -> 30000 | J64: 3400 | L64: 405 | M64: 6300 | N64: 4110 | O64: 180 | P64: =315+7510+2040 -> 9865 | Q64: =SUM(I64:P64) -> 24260 | R64: =Q64/H64 -> 0.80866667 | S64: =H64-Q64 -> 5740 | V64: =S64 -> 5740
B65: 056 | C65: GENERAL | D65: Final Clean | F65: 50000 | H65: =F65+G65 -> 50000 | Q65: =SUM(I65:P65) -> 0 | R65: =Q65/H65 -> 0 | S65: =H65-Q65 -> 50000 | V65: =S65 -> 50000
B66: 057 | C66: GENERAL | D66: Street Sweeping | F66: 5000 | H66: =F66+G66 -> 5000 | Q66: =SUM(I66:P66) -> 0 | R66: =Q66/H66 -> 0 | S66: =H66-Q66 -> 5000 | V66: =S66 -> 5000
B67: 058 | C67: GENERAL | D67: Conc Wash Out | F67: 5000 | H67: =F67+G67 -> 5000 | Q67: =SUM(I67:P67) -> 0 | R67: =Q67/H67 -> 0 | S67: =H67-Q67 -> 5000 | V67: =S67 -> 5000
B68: 059 | C68: GENERAL | D68: SWPPP/split w/cu inspections | F68: 3500 | G68: 140 | H68: =F68+G68 -> 3640 | I68: 450 | J68: 450 | K68: 940 | L68: 450 | M68: 450 | N68: 450 | O68: 450 | P68: =750+450+450 -> 1650 | Q68: =SUM(I68:P68) -> 5290 | R68: =Q68/H68 -> 1.4532967 | S68: =H68-Q68 -> -1650 | V68: 1500
B69: 060 | C69: GENERAL | D69: Temp Power | F69: 7500 | H69: =F69+G69 -> 7500 | I69: 216.17 | J69: 122.62 | K69: =437.71+2600 -> 3037.71 | L69: 152.71 | M69: =11.2+57.42 -> 68.62 | N69: 368.53 | O69: =968.6+23.17 -> 991.77 | P69: =594.15+34.6+210.01 -> 838.76 | Q69: =SUM(I69:P69) -> 5796.89 | R69: =Q69/H69 -> 0.77291867 | S69: =H69-Q69 -> 1703.11 | V69: =S69 -> 1703.11
B70: 061 | C70: GENERAL | D70: Office Trailer | F70: 15000 | H70: =F70+G70 -> 15000 | K70: 100 | L70: =50+2096.73 -> 2146.73 | M70: =2096.73+2096.73+22.62 -> 4216.08 | P70: 538.58 | Q70: =SUM(I70:P70) -> 7001.39 | R70: =Q70/H70 -> 0.46675933 | S70: =H70-Q70 -> 7998.61 | V70: =S70 -> 7998.61
B71: 062 | C71: GENERAL | D71: Security Cameras | F71: 30000 | H71: =F71+G71 -> 30000 | J71: 5641.15 | K71: =1128.23 -> 1128.23 | L71: 1128.23 | N71: =1250+1019.02+1128.23+1128.23 -> 4525.48 | P71: =1000+1800+1128.23 -> 3928.23 | Q71: =SUM(I71:P71) -> 16351.32 | R71: =Q71/H71 -> 0.545044 | S71: =H71-Q71 -> 13648.68 | V71: 5000
B72: 063 | C72: GENERAL | D72: Special Inspections | F72: 15000 | H72: =F72+G72 -> 15000 | I72: 5742.5 | J72: 4661.18 | M72: =1570+1920 -> 3490 | N72: 500 | Q72: =SUM(I72:P72) -> 14393.68 | R72: =Q72/H72 -> 0.95957867 | S72: =H72-Q72 -> 606.32 | V72: 0
B73: 064 | C73: GENERAL | D73: Saftey | F73: 10000 | G73: -5000 | H73: =F73+G73 -> 5000 | Q73: =SUM(I73:P73) -> 0 | R73: =Q73/H73 -> 0 | S73: =H73-Q73 -> 5000 | V73: =S73 -> 5000
B74: 065 | C74: GENERAL | D74: General Conditions | F74: 30000 | H74: =F74+G74 -> 30000 | J74: 779.31 | M74: =1258.23+781.19+916.99+178.67 -> 3135.08 | P74: =6000+2469.08 -> 8469.08 | Q74: =SUM(I74:P74) -> 12383.47 | R74: =Q74/H74 -> 0.41278233 | S74: =H74-Q74 -> 17616.53 | V74: =S74 -> 17616.53
B75: 066 | C75: GENERAL | D75: Insurance Not Builders | F75: 25000 | H75: =F75+G75 -> 25000 | J75: 19.98 | Q75: =SUM(I75:P75) -> 19.98 | R75: =Q75/H75 -> 0.0007992 | S75: =H75-Q75 -> 24980.02 | V75: 0
B76: 067 | C76: GENERAL | D76: Site Supervision | F76: 240000 | H76: =F76+G76 -> 240000 | I76: 25000 | J76: 20000 | K76: =36000+5500 -> 41500 | L76: =25000+4000 -> 29000 | M76: =3200+20175 -> 23375 | N76: =20175+2000 -> 22175 | O76: 22175 | P76: 60525 | Q76: =SUM(I76:P76) -> 243750 | R76: =Q76/H76 -> 1.015625 | S76: =H76-Q76 -> -3750 | V76: =S76 -> -3750
B77: 068 | C77: GENERAL | D77: Construction Profit | F77: 6583.94 | H77: =F77+G77 -> 6583.94 | Q77: =SUM(I77:P77) -> 0 | R77: =Q77/H77 -> 0 | S77: =H77-Q77 -> 6583.94 | V77: 606582.94
B78: 069 | C78: GENERAL | D78: Exterior Wall Project | F78: 483915.5 | G78: 276202.41 | H78: =F78+G78 -> 760117.91 | I78: 204487 | J78: 279428.5 | K78: =862.22+1014.52+98198.01+37611.1+49995+28373.32 -> 216054.17 | L78: =12925+6949.8+1982.83+128.41+1752.7 -> 23738.74 | M78: 18672.5 | O78: 17737 | P78: =5550+175+175+2895+70878.05-5429.33 -> 74243.72 | Q78: =SUM(I78:P78) -> 834361.63 | R78: =Q78/H78 -> 1.097674 | S78: =H78-Q78 -> -74243.72 | U78: SCS | V78: 200000 | X78: 201701 | Y78: Plumbing fixes
D80: TOTALS | F80: =SUM(F10:F79) -> 10159856 | G80: =SUM(G10:G79) -> 0 | H80: =SUM(H10:H79) -> 10159856 | I80: =SUM(I10:I78) -> 430727.04 | J80: =SUM(J10:J78) -> 620765.82 | K80: =SUM(K10:K78) -> 1448767.7 | L80: =SUM(L10:L78) -> 1069457.4 | M80: =SUM(M10:M78) -> 1367102.4 | N80: =SUM(N10:N78) -> 535818.07 | O80: =SUM(O10:O78) -> 1577307.3 | P80: =SUM(P10:P78) -> 1905850.9 | Q80: =SUM(Q10:Q78) -> 8955796.7 | R80: =Q80/F80 -> 0.88148854 | S80: =F80-Q80 -> 1204059.4 | T80: =SUM(T10:T78) -> 0
C81: GENERAL | D81: 1st MTG IR | F81: 494000 | H81: =F81+G81 -> 494000 | J81: 163759.91 | Q81: =SUM(I81:O81) -> 163759.91 | R81: =Q81/F81 -> 0.33149779 | S81: =F81-Q81 -> 330240.09
C82: GENERAL | D82: 2nd MTG IR | F82: 550497.32 | H82: =F82+G82 -> 550497.32 | Q82: =SUM(I82:O82) -> 0 | R82: =Q82/F82 -> 0 | S82: =F82-Q82 -> 550497.32
C83: GENERAL | D83: Inspections | F83: 3500 | H83: =F83+G83 -> 3500 | J83: 800 | Q83: =SUM(I83:O83) -> 800 | R83: =Q83/F83 -> 0.22857143 | S83: =F83-Q83 -> 2700
D84: TOTALS | F84: =SUM(F80:F83) -> 11207853 | G84: =SUM(G80:G83) -> 0 | H84: =SUM(H80:H83) -> 11207853 | I84: =SUM(I80:I83) -> 430727.04 | J84: =SUM(J80:J83) -> 785325.73 | K84: =SUM(K80:K83) -> 1448767.7 | L84: =SUM(L80:L83) -> 1069457.4 | M84: =SUM(M80:M83) -> 1367102.4 | ... O84: =SUM(O80:O83) -> 1577307.3 | Q84: =SUM(Q80:Q83) -> 9120356.6 | R84: =Q84/F84 -> 0.81374695 | S84: =F84-Q84 -> 2087496.8 | T84: =SUM(T80:T83) -> 0
Q85: =Q80-SUM(I80:N80) -> 3483158.2
F86: Cash
F87: Loan | Q87: =S80-9991800.69 -> -8787741.3
F89: Original Contract Sum | U89: TOTAL | V89: =SUM(V10:V88) -> 2340391.4 | X89: =SUM(X10:X88) -> 542236.26
F90: Net change by approved change orders
F91: Contract sum to date | U91: GRAND TOTAL | V91: =SUM(V89:X89) -> 2882627.6
F92: Total completed and stored to date
F93: Retainage
F94: Total earned less retainage
F95: Less previous certificates for payment
F96: Current Payment Due
F97: Balance to finish with retainage

Sheet Future Costs
B5: Subs
B6: Fortified | D6: Corbin
A7: Ignore first CO | B7: Fox and Hound
A8: Will cost a bit more | B8: Landscaping
A9: Go with contract amount | B9: TK
A10: Look into rubber base | B10: Poulson | D10: Corbin
B11: Cleaners | D11: Corbin
A12: Add paint bills into cost & do a deduct on fox & hound | B12: PPC
B13: My Roof
B14: Lara and Sons
B15: Korey
B16: Sunrise Elite
B17: Douggie Fresh
B18: Select Specialties
B19: Toilets
B20: Dumpsters
B21: Shed
B22: Security Cameras
B23: Lock up at night security
B24: Equipment For cabients
... B41: Abrams
